{"businesses": [{"coordinates": {"longitude": -122.340060726984, "latitude": 47.6132519777742}, "categories": [{"alias": "greek", "title": "Greek"}, {"alias": "mediterranean", "title": "Mediterranean"}, {"alias": "breakfast_brunch", "title": "Breakfast & Brunch"}], "location": {"display_address": ["2000 4th Ave", "Seattle, WA 98121"], "address3": "", "city": "Seattle", "state": "WA", "address2": null, "address1": "2000 4th Ave", "zip_code": "98121", "country": "US"}, "review_count": 2832, "distance": 1395.377281396, "display_phone": "(206) 441-1430", "price": "$$", "rating": 4.0, "phone": "+12064411430", "id": "lola-seattle", "name": "Lola", "transactions": [], "url": "https://www.yelp.com/biz/lola-seattle?adjust_creative=8_C4NSGbL05eUQksKleGYw&utm_campaign=yelp_api_v3&utm_medium=api_v3_business_search&utm_source=8_C4NSGbL05eUQksKleGYw", "is_closed": false, "image_url": "https://s3-media3.fl.yelpcdn.com/bphoto/EeM89mDr70_ziqrjUb3gEg/o.jpg"}, {"coordinates": {"longitude": -122.3541946, "latitude": 47.6520309}, "categories": [{"alias": "asianfusion", "title": "Asian Fusion"}, {"alias": "korean", "title": "Korean"}], "location": {"display_address": ["403 N 36th St", "Seattle, WA 98103"], "address3": "", "city": "Seattle", "state": "WA", "address2": "", "address1": "403 N 36th St", "zip_code": "98103", "country": "US"}, "review_count": 1064, "distance": 3262.5630003179995, "display_phone": "(206) 547-2040", "price": "$$", "rating": 4.0, "phone": "+12065472040", "id": "revel-seattle", "name": "Revel", "transactions": [], "url": "https://www.yelp.com/biz/revel-seattle?adjust_creative=8_C4NSGbL05eUQksKleGYw&utm_campaign=yelp_api_v3&utm_medium=api_v3_business_search&utm_source=8_C4NSGbL05eUQksKleGYw", "is_closed": false, "image_url": "https://s3-media1.fl.yelpcdn.com/bphoto/oXYP3CPy6Fv7Z3Lb02xaWw/o.jpg"}, {"coordinates": {"longitude": -122.320680460381, "latitude": 47.6225508133524}, "categories": [{"alias": "southern", "title": "Southern"}, {"alias": "cocktailbars", "title": "Cocktail Bars"}], "location": {"display_address": ["410 Broadway E", "Seattle, WA 98102"], "address3": "", "city": "Seattle", "state": "WA", "address2": "", "address1": "410 Broadway E", "zip_code": "98102", "country": "US"}, "review_count": 542, "distance": 1156.4064491696, "display_phone": "(206) 329-0248", "price": "$$", "rating": 4.5, "phone": "+12063290248", "id": "witness-seattle", "name": "Witness", "transactions": [], "url": "https://www.yelp.com/biz/witness-seattle?adjust_creative=8_C4NSGbL05eUQksKleGYw&utm_campaign=yelp_api_v3&utm_medium=api_v3_business_search&utm_source=8_C4NSGbL05eUQksKleGYw", "is_closed": false, "image_url": "https://s3-media2.fl.yelpcdn.com/bphoto/YP0ez-LJGz901A4_2ggD7g/o.jpg"}, {"coordinates": {"longitude": -122.3342613, "latitude": 47.6088937}, "categories": [{"alias": "korean", "title": "Korean"}, {"alias": "buffets", "title": "Buffets"}], "location": {"display_address": ["1301 5th Ave", "Concourse", "Seattle, WA 98101"], "address3": "", "city": "Seattle", "state": "WA", "address2": "Concourse", "address1": "1301 5th Ave", "zip_code": "98101", "country": "US"}, "review_count": 289, "distance": 1839.91577449, "display_phone": "(206) 854-3166", "price": "$", "rating": 4.5, "phone": "+12068543166", "id": "ummas-lunch-box-seattle", "name": "Umma's Lunch Box", "transactions": [], "url": "https://www.yelp.com/biz/ummas-lunch-box-seattle?adjust_creative=8_C4NSGbL05eUQksKleGYw&utm_campaign=yelp_api_v3&utm_medium=api_v3_business_search&utm_source=8_C4NSGbL05eUQksKleGYw", "is_closed": false, "image_url": "https://s3-media4.fl.yelpcdn.com/bphoto/1Cq7uSCEgC7xsb-MXJ-AQg/o.jpg"}, {"coordinates": {"longitude": -122.320748173641, "latitude": 47.6236055711029}, "categories": [{"alias": "tapasmallplates", "title": "Tapas/Small Plates"}], "location": {"display_address": ["516 Broadway E", "Seattle, WA 98102"], "address3": "", "city": "Seattle", "state": "WA", "address2": "", "address1": "516 Broadway E", "zip_code": "98102", "country": "US"}, "review_count": 175, "distance": 1124.6583552536, "display_phone": "(206) 708-6468", "price": "$$", "rating": 4.5, "phone": "+12067086468", "id": "herb-and-bitter-public-house-seattle", "name": "Herb & Bitter Public House", "transactions": [], "url": "https://www.yelp.com/biz/herb-and-bitter-public-house-seattle?adjust_creative=8_C4NSGbL05eUQksKleGYw&utm_campaign=yelp_api_v3&utm_medium=api_v3_business_search&utm_source=8_C4NSGbL05eUQksKleGYw", "is_closed": false, "image_url": "https://s3-media1.fl.yelpcdn.com/bphoto/f5YI3sxCilf0PrPxyFgwHQ/o.jpg"}, {"coordinates": {"longitude": -122.355570159853, "latitude": 47.6904199617095}, "categories": [{"alias": "newamerican", "title": "American (New)"}, {"alias": "steak", "title": "Steakhouses"}, {"alias": "cocktailbars", "title": "Cocktail Bars"}], "location": {"display_address": ["8421 Greenwood Ave N", "Seattle, WA 98103"], "address3": null, "city": "Seattle", "state": "WA", "address2": "", "address1": "8421 Greenwood Ave N", "zip_code": "98103", "country": "US"}, "review_count": 97, "distance": 7381.978689202, "display_phone": "(206) 457-5656", "price": "$$$", "rating": 4.5, "phone": "+12064575656", "id": "flintcreek-cattle-seattle-2", "name": "Flintcreek Cattle", "transactions": [], "url": "https://www.yelp.com/biz/flintcreek-cattle-seattle-2?adjust_creative=8_C4NSGbL05eUQksKleGYw&utm_campaign=yelp_api_v3&utm_medium=api_v3_business_search&utm_source=8_C4NSGbL05eUQksKleGYw", "is_closed": false, "image_url": "https://s3-media3.fl.yelpcdn.com/bphoto/uJRirZgDnaJhj01GN_HJXA/o.jpg"}, {"coordinates": {"longitude": -122.3467676, "latitude": 47.6430119}, "categories": [{"alias": "newamerican", "title": "American (New)"}, {"alias": "seafood", "title": "Seafood"}], "location": {"display_address": ["2576 Aurora Ave N", "Seattle, WA 98109"], "address3": "", "city": "Seattle", "state": "WA", "address2": "", "address1": "2576 Aurora Ave N", "zip_code": "98109", "country": "US"}, "review_count": 1069, "distance": 2130.50544692, "display_phone": "(206) 283-3313", "price": "$$$$", "rating": 4.0, "phone": "+12062833313", "id": "canlis-seattle", "name": "Canlis", "transactions": [], "url": "https://www.yelp.com/biz/canlis-seattle?adjust_creative=8_C4NSGbL05eUQksKleGYw&utm_campaign=yelp_api_v3&utm_medium=api_v3_business_search&utm_source=8_C4NSGbL05eUQksKleGYw", "is_closed": false, "image_url": "https://s3-media2.fl.yelpcdn.com/bphoto/1mQGcg9DhUrQYu3mKh9XXA/o.jpg"}, {"coordinates": {"longitude": -122.34782409668, "latitude": 47.6270141601562}, "categories": [{"alias": "newamerican", "title": "American (New)"}, {"alias": "modern_european", "title": "Modern European"}], "location": {"display_address": ["823 5th Ave N", "Seattle, WA 98109"], "address3": "", "city": "Seattle", "state": "WA", "address2": null, "address1": "823 5th Ave N", "zip_code": "98109", "country": "US"}, "review_count": 466, "distance": 940.3362354619999, "display_phone": "(206) 283-8800", "price": "$$", "rating": 4.0, "phone": "+12062838800", "id": "crow-seattle", "name": "Crow", "transactions": [], "url": "https://www.yelp.com/biz/crow-seattle?adjust_creative=8_C4NSGbL05eUQksKleGYw&utm_campaign=yelp_api_v3&utm_medium=api_v3_business_search&utm_source=8_C4NSGbL05eUQksKleGYw", "is_closed": false, "image_url": "https://s3-media1.fl.yelpcdn.com/bphoto/woD4GzR78vnhHAHqb3F1WA/o.jpg"}, {"coordinates": {"longitude": -122.34047, "latitude": 47.61296}, "categories": [{"alias": "pizza", "title": "Pizza"}], "location": {"display_address": ["316 Virginia St", "Seattle, WA 98121"], "address3": "", "city": "Seattle", "state": "WA", "address2": null, "address1": "316 Virginia St", "zip_code": "98121", "country": "US"}, "review_count": 3238, "distance": 1443.5519086919999, "display_phone": "(206) 838-7388", "price": "$$", "rating": 4.0, "phone": "+12068387388", "id": "serious-pie-seattle", "name": "Serious Pie", "transactions": [], "url": "https://www.yelp.com/biz/serious-pie-seattle?adjust_creative=8_C4NSGbL05eUQksKleGYw&utm_campaign=yelp_api_v3&utm_medium=api_v3_business_search&utm_source=8_C4NSGbL05eUQksKleGYw", "is_closed": false, "image_url": "https://s3-media3.fl.yelpcdn.com/bphoto/lxOPztcQq9URv7h4K2juOA/o.jpg"}, {"coordinates": {"longitude": -122.33165, "latitude": 47.60244}, "categories": [{"alias": "italian", "title": "Italian"}, {"alias": "noodles", "title": "Noodles"}, {"alias": "pastashops", "title": "Pasta Shops"}], "location": {"display_address": ["217 James St", "Seattle, WA 98104"], "address3": "", "city": "Seattle", "state": "WA", "address2": "", "address1": "217 James St", "zip_code": "98104", "country": "US"}, "review_count": 615, "distance": 2574.84422092, "display_phone": "(206) 538-0999", "price": "$$", "rating": 4.5, "phone": "+12065380999", "id": "il-corvo-pasta-seattle", "name": "Il Corvo Pasta", "transactions": [], "url": "https://www.yelp.com/biz/il-corvo-pasta-seattle?adjust_creative=8_C4NSGbL05eUQksKleGYw&utm_campaign=yelp_api_v3&utm_medium=api_v3_business_search&utm_source=8_C4NSGbL05eUQksKleGYw", "is_closed": false, "image_url": "https://s3-media1.fl.yelpcdn.com/bphoto/5lon1Dkb7r1rbEf5z8qdow/o.jpg"}, {"coordinates": {"longitude": -122.331748962402, "latitude": 47.6288185119629}, "categories": [{"alias": "seafood", "title": "Seafood"}, {"alias": "cocktailbars", "title": "Cocktail Bars"}, {"alias": "venues", "title": "Venues & Event Spaces"}], "location": {"display_address": ["1001 Fairview Ave N", "Seattle, WA 98109"], "address3": null, "city": "Seattle", "state": "WA", "address2": "", "address1": "1001 Fairview Ave N", "zip_code": "98109", "country": "US"}, "review_count": 62, "distance": 485.3898670002, "display_phone": "(206) 588-2680", "price": "$$", "rating": 4.5, "phone": "+12065882680", "id": "the-white-swan-public-house-seattle-2", "name": "The White Swan Public House", "transactions": [], "url": "https://www.yelp.com/biz/the-white-swan-public-house-seattle-2?adjust_creative=8_C4NSGbL05eUQksKleGYw&utm_campaign=yelp_api_v3&utm_medium=api_v3_business_search&utm_source=8_C4NSGbL05eUQksKleGYw", "is_closed": false, "image_url": "https://s3-media2.fl.yelpcdn.com/bphoto/U_vu2eO_uOwcJjmXC8JRuA/o.jpg"}, {"coordinates": {"longitude": -122.342521548271, "latitude": 47.6099207997322}, "categories": [{"alias": "bakeries", "title": "Bakeries"}, {"alias": "russian", "title": "Russian"}], "location": {"display_address": ["1908 Pike Pl", "Seattle, WA 98101"], "address3": "", "city": "Seattle", "state": "WA", "address2": "", "address1": "1908 Pike Pl", "zip_code": "98101", "country": "US"}, "review_count": 4124, "distance": 1796.768886288, "display_phone": "(206) 441-6068", "price": "$", "rating": 4.5, "phone": "+12064416068", "id": "piroshky-piroshky-seattle", "name": "Piroshky Piroshky", "transactions": [], "url": "https://www.yelp.com/biz/piroshky-piroshky-seattle?adjust_creative=8_C4NSGbL05eUQksKleGYw&utm_campaign=yelp_api_v3&utm_medium=api_v3_business_search&utm_source=8_C4NSGbL05eUQksKleGYw", "is_closed": false, "image_url": "https://s3-media4.fl.yelpcdn.com/bphoto/yjqyb9elWeiFonXkmDiJmA/o.jpg"}, {"coordinates": {"longitude": -122.37011, "latitude": 47.62738}, "categories": [{"alias": "korean", "title": "Korean"}, {"alias": "mexican", "title": "Mexican"}, {"alias": "cocktailbars", "title": "Cocktail Bars"}], "location": {"display_address": ["945 Elliott Ave W", "Ste 201", "Seattle, WA 98119"], "address3": "", "city": "Seattle", "state": "WA", "address2": "Ste 201", "address1": "945 Elliott Ave W", "zip_code": "98119", "country": "US"}, "review_count": 54, "distance": 2584.0797403779998, "display_phone": "(206) 588-2224", "price": "$$", "rating": 4.5, "phone": "+12065882224", "id": "citizen-six-seattle", "name": "Citizen Six", "transactions": [], "url": "https://www.yelp.com/biz/citizen-six-seattle?adjust_creative=8_C4NSGbL05eUQksKleGYw&utm_campaign=yelp_api_v3&utm_medium=api_v3_business_search&utm_source=8_C4NSGbL05eUQksKleGYw", "is_closed": false, "image_url": "https://s3-media3.fl.yelpcdn.com/bphoto/8lNJTZ4sNkUU5HEF3rab7Q/o.jpg"}, {"coordinates": {"longitude": -122.2849313, "latitude": 47.6021513}, "categories": [{"alias": "desserts", "title": "Desserts"}, {"alias": "breakfast_brunch", "title": "Breakfast & Brunch"}, {"alias": "bars", "title": "Bars"}], "location": {"display_address": ["120 Lakeside Ave", "Seattle, WA 98122"], "address3": "", "city": "Seattle", "state": "WA", "address2": "", "address1": "120 Lakeside Ave", "zip_code": "98122", "country": "US"}, "review_count": 161, "distance": 4589.9075253559995, "display_phone": "(206) 707-9730", "price": "$$", "rating": 4.5, "phone": "+12067079730", "id": "meet-the-moon-seattle", "name": "Meet the Moon", "transactions": [], "url": "https://www.yelp.com/biz/meet-the-moon-seattle?adjust_creative=8_C4NSGbL05eUQksKleGYw&utm_campaign=yelp_api_v3&utm_medium=api_v3_business_search&utm_source=8_C4NSGbL05eUQksKleGYw", "is_closed": false, "image_url": "https://s3-media1.fl.yelpcdn.com/bphoto/Q4WFcsgSGBQ8q2sjpFgruA/o.jpg"}, {"coordinates": {"longitude": -122.3328506, "latitude": 47.6133323}, "categories": [{"alias": "newamerican", "title": "American (New)"}, {"alias": "bars", "title": "Bars"}, {"alias": "vegetarian", "title": "Vegetarian"}], "location": {"display_address": ["820 Pine St", "Seattle, WA 98101"], "address3": "", "city": "Seattle", "state": "WA", "address2": "", "address1": "820 Pine St", "zip_code": "98101", "country": "US"}, "review_count": 232, "distance": 1332.752068372, "display_phone": "(206) 946-9720", "price": "$$", "rating": 4.0, "phone": "+12069469720", "id": "the-carlile-room-seattle", "name": "The Carlile Room", "transactions": [], "url": "https://www.yelp.com/biz/the-carlile-room-seattle?adjust_creative=8_C4NSGbL05eUQksKleGYw&utm_campaign=yelp_api_v3&utm_medium=api_v3_business_search&utm_source=8_C4NSGbL05eUQksKleGYw", "is_closed": false, "image_url": "https://s3-media2.fl.yelpcdn.com/bphoto/avjOYlEre1rJVepmNANoYg/o.jpg"}, {"coordinates": {"longitude": -122.39916, "latitude": 47.64026}, "categories": [{"alias": "japanese", "title": "Japanese"}, {"alias": "korean", "title": "Korean"}, {"alias": "asianfusion", "title": "Asian Fusion"}], "location": {"display_address": ["3216 W Wheeler St", "Seattle, WA 98199"], "address3": "", "city": "Seattle", "state": "WA", "address2": "", "address1": "3216 W Wheeler St", "zip_code": "98199", "country": "US"}, "review_count": 63, "distance": 5044.026580404, "display_phone": "(206) 390-7148", "price": "$$", "rating": 4.5, "phone": "+12063907148", "id": "mura-asian-eatery-seattle", "name": "Mura Asian Eatery", "transactions": [], "url": "https://www.yelp.com/biz/mura-asian-eatery-seattle?adjust_creative=8_C4NSGbL05eUQksKleGYw&utm_campaign=yelp_api_v3&utm_medium=api_v3_business_search&utm_source=8_C4NSGbL05eUQksKleGYw", "is_closed": false, "image_url": "https://s3-media4.fl.yelpcdn.com/bphoto/lz5mC0TFEkcDlBz3ZFM7fA/o.jpg"}, {"coordinates": {"longitude": -122.3389893, "latitude": 47.6080894}, "categories": [{"alias": "japanese", "title": "Japanese"}, {"alias": "sushi", "title": "Sushi Bars"}], "location": {"display_address": ["1400 1st Ave", "Seattle, WA 98101"], "address3": "", "city": "Seattle", "state": "WA", "address2": "", "address1": "1400 1st Ave", "zip_code": "98101", "country": "US"}, "review_count": 3063, "distance": 1952.771385726, "display_phone": "(206) 971-7979", "price": "$$", "rating": 4.0, "phone": "+12069717979", "id": "japonessa-seattle", "name": "Japonessa", "transactions": [], "url": "https://www.yelp.com/biz/japonessa-seattle?adjust_creative=8_C4NSGbL05eUQksKleGYw&utm_campaign=yelp_api_v3&utm_medium=api_v3_business_search&utm_source=8_C4NSGbL05eUQksKleGYw", "is_closed": false, "image_url": "https://s3-media3.fl.yelpcdn.com/bphoto/vucCrknnlu1RRvRaKWwovQ/o.jpg"}, {"coordinates": {"longitude": -122.34895, "latitude": 47.64972}, "categories": [{"alias": "newamerican", "title": "American (New)"}], "location": {"display_address": ["704 N 34th St", "Seattle, WA 98103"], "address3": "", "city": "Seattle", "state": "WA", "address2": "", "address1": "704 N 34th St", "zip_code": "98103", "country": "US"}, "review_count": 121, "distance": 2887.15596, "display_phone": "(206) 900-7186", "price": "$$", "rating": 4.0, "phone": "+12069007186", "id": "eve-fremont-seattle", "name": "Eve Fremont", "transactions": [], "url": "https://www.yelp.com/biz/eve-fremont-seattle?adjust_creative=8_C4NSGbL05eUQksKleGYw&utm_campaign=yelp_api_v3&utm_medium=api_v3_business_search&utm_source=8_C4NSGbL05eUQksKleGYw", "is_closed": false, "image_url": "https://s3-media4.fl.yelpcdn.com/bphoto/tdvpetnRMdkLJLjcKOWEYg/o.jpg"}, {"coordinates": {"longitude": -122.34105, "latitude": 47.60871}, "categories": [{"alias": "newamerican", "title": "American (New)"}, {"alias": "breakfast_brunch", "title": "Breakfast & Brunch"}, {"alias": "cocktailbars", "title": "Cocktail Bars"}], "location": {"display_address": ["1501 Pike Pl", "Ste 200", "Seattle, WA 98101"], "address3": "", "city": "Seattle", "state": "WA", "address2": "Ste 200", "address1": "1501 Pike Pl", "zip_code": "98101", "country": "US"}, "review_count": 112, "distance": 1943.886219586, "display_phone": "(206) 538-0377", "price": "$$", "rating": 4.5, "phone": "+12065380377", "id": "red-cedar-and-sage-seattle", "name": "Red Cedar & Sage", "transactions": [], "url": "https://www.yelp.com/biz/red-cedar-and-sage-seattle?adjust_creative=8_C4NSGbL05eUQksKleGYw&utm_campaign=yelp_api_v3&utm_medium=api_v3_business_search&utm_source=8_C4NSGbL05eUQksKleGYw", "is_closed": false, "image_url": "https://s3-media2.fl.yelpcdn.com/bphoto/2WkgVvTxaYJTeVOoysTk2w/o.jpg"}, {"coordinates": {"longitude": -122.34843313694, "latitude": 47.615292215253}, "categories": [{"alias": "beerbar", "title": "Beer Bar"}, {"alias": "newamerican", "title": "American (New)"}, {"alias": "gastropubs", "title": "Gastropubs"}], "location": {"display_address": ["2505 2nd Ave", "Ste 105", "Seattle, WA 98121"], "address3": null, "city": "Seattle", "state": "WA", "address2": "Ste 105", "address1": "2505 2nd Ave", "zip_code": "98121", "country": "US"}, "review_count": 54, "distance": 1485.463145642, "display_phone": "(206) 448-2610", "price": "$$", "rating": 4.0, "phone": "+12064482610", "id": "no-anchor-seattle-3", "name": "No Anchor", "transactions": [], "url": "https://www.yelp.com/biz/no-anchor-seattle-3?adjust_creative=8_C4NSGbL05eUQksKleGYw&utm_campaign=yelp_api_v3&utm_medium=api_v3_business_search&utm_source=8_C4NSGbL05eUQksKleGYw", "is_closed": false, "image_url": "https://s3-media2.fl.yelpcdn.com/bphoto/USnMAciQYl6SdRG4xsoQzw/o.jpg"}, {"coordinates": {"longitude": -122.387145996094, "latitude": 47.5742950439453}, "categories": [{"alias": "newamerican", "title": "American (New)"}], "location": {"display_address": ["3247 California Ave SW", "Seattle, WA 98116"], "address3": "", "city": "Seattle", "state": "WA", "address2": "", "address1": "3247 California Ave SW", "zip_code": "98116", "country": "US"}, "review_count": 217, "distance": 6877.943379109999, "display_phone": "(206) 257-4832", "price": "$$", "rating": 4.5, "phone": "+12062574832", "id": "blackboard-bistro-seattle", "name": "Blackboard Bistro", "transactions": [], "url": "https://www.yelp.com/biz/blackboard-bistro-seattle?adjust_creative=8_C4NSGbL05eUQksKleGYw&utm_campaign=yelp_api_v3&utm_medium=api_v3_business_search&utm_source=8_C4NSGbL05eUQksKleGYw", "is_closed": false, "image_url": "https://s3-media4.fl.yelpcdn.com/bphoto/5uhJwDFOQ7EqWp9cL_LXzw/o.jpg"}, {"coordinates": {"longitude": -122.356887666769, "latitude": 47.6385402665478}, "categories": [{"alias": "italian", "title": "Italian"}, {"alias": "tapasmallplates", "title": "Tapas/Small Plates"}], "location": {"display_address": ["2208 Queen Anne Ave N", "Seattle, WA 98109"], "address3": "", "city": "Seattle", "state": "WA", "address2": "", "address1": "2208 Queen Anne Ave N", "zip_code": "98109", "country": "US"}, "review_count": 724, "distance": 2166.55305358, "display_phone": "(206) 838-8090", "price": "$$$", "rating": 4.0, "phone": "+12068388090", "id": "how-to-cook-a-wolf-seattle", "name": "How To Cook a Wolf", "transactions": [], "url": "https://www.yelp.com/biz/how-to-cook-a-wolf-seattle?adjust_creative=8_C4NSGbL05eUQksKleGYw&utm_campaign=yelp_api_v3&utm_medium=api_v3_business_search&utm_source=8_C4NSGbL05eUQksKleGYw", "is_closed": false, "image_url": "https://s3-media4.fl.yelpcdn.com/bphoto/cueM2F4flV-JySEhJ-q_wQ/o.jpg"}, {"coordinates": {"longitude": -122.340225, "latitude": 47.605056}, "categories": [{"alias": "seafood", "title": "Seafood"}, {"alias": "raw_food", "title": "Live/Raw Food"}, {"alias": "cafes", "title": "Cafes"}], "location": {"display_address": ["1201 Alaskan Way", "Pier 56", "Seattle, WA 98101"], "address3": "Pier 56", "city": "Seattle", "state": "WA", "address2": "", "address1": "1201 Alaskan Way", "zip_code": "98101", "country": "US"}, "review_count": 2213, "distance": 2256.33008548, "display_phone": "(206) 623-4340", "price": "$$$", "rating": 4.0, "phone": "+12066234340", "id": "elliotts-oyster-house-seattle-2", "name": "Elliott's Oyster House", "transactions": [], "url": "https://www.yelp.com/biz/elliotts-oyster-house-seattle-2?adjust_creative=8_C4NSGbL05eUQksKleGYw&utm_campaign=yelp_api_v3&utm_medium=api_v3_business_search&utm_source=8_C4NSGbL05eUQksKleGYw", "is_closed": false, "image_url": "https://s3-media3.fl.yelpcdn.com/bphoto/Am6AabmBhkHHqrGRSg2clQ/o.jpg"}, {"coordinates": {"longitude": -122.3390033, "latitude": 47.626012}, "categories": [{"alias": "bbq", "title": "Barbeque"}, {"alias": "bars", "title": "Bars"}, {"alias": "tradamerican", "title": "American (Traditional)"}], "location": {"display_address": ["711 Westlake Ave", "Seattle, WA 98109"], "address3": "", "city": "Seattle", "state": "WA", "address2": "", "address1": "711 Westlake Ave", "zip_code": "98109", "country": "US"}, "review_count": 350, "distance": 269.9946748622, "display_phone": "(206) 453-4756", "price": "$$", "rating": 4.0, "phone": "+12064534756", "id": "cask-and-trotter-seattle-2", "name": "Cask & Trotter", "transactions": [], "url": "https://www.yelp.com/biz/cask-and-trotter-seattle-2?adjust_creative=8_C4NSGbL05eUQksKleGYw&utm_campaign=yelp_api_v3&utm_medium=api_v3_business_search&utm_source=8_C4NSGbL05eUQksKleGYw", "is_closed": false, "image_url": "https://s3-media2.fl.yelpcdn.com/bphoto/SIMC_YGPyow4E_b3FwSJeA/o.jpg"}, {"coordinates": {"longitude": -122.35575, "latitude": 47.6257}, "categories": [{"alias": "bars", "title": "Bars"}, {"alias": "pizza", "title": "Pizza"}], "location": {"display_address": ["20 Roy St", "Seattle, WA 98109"], "address3": "", "city": "Seattle", "state": "WA", "address2": "", "address1": "20 Roy St", "zip_code": "98109", "country": "US"}, "review_count": 237, "distance": 1519.3577772499998, "display_phone": "(206) 453-4375", "price": "$$", "rating": 4.0, "phone": "+12064534375", "id": "the-masonry-seattle", "name": "The Masonry", "transactions": [], "url": "https://www.yelp.com/biz/the-masonry-seattle?adjust_creative=8_C4NSGbL05eUQksKleGYw&utm_campaign=yelp_api_v3&utm_medium=api_v3_business_search&utm_source=8_C4NSGbL05eUQksKleGYw", "is_closed": false, "image_url": "https://s3-media2.fl.yelpcdn.com/bphoto/cLFd5EE0XXwFNUmjEECvYw/o.jpg"}, {"coordinates": {"longitude": -122.3329512, "latitude": 47.6686946}, "categories": [{"alias": "newamerican", "title": "American (New)"}], "location": {"display_address": ["2108 N 55th St", "Seattle, WA 98103"], "address3": "", "city": "Seattle", "state": "WA", "address2": "", "address1": "2108 N 55th St", "zip_code": "98103", "country": "US"}, "review_count": 207, "distance": 4815.643048862, "display_phone": "(206) 812-1580", "price": "$$$", "rating": 4.5, "phone": "+12068121580", "id": "mkt-seattle", "name": "mkt.", "transactions": [], "url": "https://www.yelp.com/biz/mkt-seattle?adjust_creative=8_C4NSGbL05eUQksKleGYw&utm_campaign=yelp_api_v3&utm_medium=api_v3_business_search&utm_source=8_C4NSGbL05eUQksKleGYw", "is_closed": false, "image_url": "https://s3-media2.fl.yelpcdn.com/bphoto/L8GR5vgepzncZO0svuYYnA/o.jpg"}, {"coordinates": {"longitude": -122.3414779, "latitude": 47.6083803}, "categories": [{"alias": "newamerican", "title": "American (New)"}, {"alias": "cocktailbars", "title": "Cocktail Bars"}], "location": {"display_address": ["1501 Western Ave", "Ste 202", "Seattle, WA 98101"], "address3": "", "city": "Seattle", "state": "WA", "address2": "Ste 202", "address1": "1501 Western Ave", "zip_code": "98101", "country": "US"}, "review_count": 780, "distance": 1946.8440255719997, "display_phone": "(206) 625-1146", "price": "$$", "rating": 4.5, "phone": "+12066251146", "id": "the-zig-zag-caf\u00e9-seattle-2", "name": "The Zig Zag Caf\u00e9", "transactions": [], "url": "https://www.yelp.com/biz/the-zig-zag-caf%C3%A9-seattle-2?adjust_creative=8_C4NSGbL05eUQksKleGYw&utm_campaign=yelp_api_v3&utm_medium=api_v3_business_search&utm_source=8_C4NSGbL05eUQksKleGYw", "is_closed": false, "image_url": "https://s3-media3.fl.yelpcdn.com/bphoto/m2ZA0NNBzdKHpJdnxxB8GQ/o.jpg"}, {"coordinates": {"longitude": -122.349802245912, "latitude": 47.6155010022786}, "categories": [{"alias": "gastropubs", "title": "Gastropubs"}, {"alias": "cocktailbars", "title": "Cocktail Bars"}, {"alias": "breakfast_brunch", "title": "Breakfast & Brunch"}], "location": {"display_address": ["2604 1st Ave", "Seattle, WA 98121"], "address3": "", "city": "Seattle", "state": "WA", "address2": null, "address1": "2604 1st Ave", "zip_code": "98121", "country": "US"}, "review_count": 547, "distance": 1537.3248513449998, "display_phone": "", "price": "$$", "rating": 4.5, "phone": "", "id": "some-random-bar-seattle", "name": "Some Random Bar", "transactions": [], "url": "https://www.yelp.com/biz/some-random-bar-seattle?adjust_creative=8_C4NSGbL05eUQksKleGYw&utm_campaign=yelp_api_v3&utm_medium=api_v3_business_search&utm_source=8_C4NSGbL05eUQksKleGYw", "is_closed": false, "image_url": "https://s3-media2.fl.yelpcdn.com/bphoto/m4hfcLhvJbEGdbgI3DhvqA/o.jpg"}, {"coordinates": {"longitude": -122.34756, "latitude": 47.61493}, "categories": [{"alias": "japanese", "title": "Japanese"}, {"alias": "hawaiian", "title": "Hawaiian"}], "location": {"display_address": ["2421 2nd Ave", "Seattle, WA 98121"], "address3": null, "city": "Seattle", "state": "WA", "address2": "", "address1": "2421 2nd Ave", "zip_code": "98121", "country": "US"}, "review_count": 42, "distance": 1479.9610696764, "display_phone": "(206) 448-3595", "price": "$$", "rating": 4.5, "phone": "+12064483595", "id": "karaage-setsuna-seattle", "name": "Karaage Setsuna", "transactions": [], "url": "https://www.yelp.com/biz/karaage-setsuna-seattle?adjust_creative=8_C4NSGbL05eUQksKleGYw&utm_campaign=yelp_api_v3&utm_medium=api_v3_business_search&utm_source=8_C4NSGbL05eUQksKleGYw", "is_closed": false, "image_url": "https://s3-media3.fl.yelpcdn.com/bphoto/8uanL36OWtKS9ec9fRNH0Q/o.jpg"}, {"coordinates": {"longitude": -122.31922, "latitude": 47.61386}, "categories": [{"alias": "newamerican", "title": "American (New)"}, {"alias": "pubs", "title": "Pubs"}], "location": {"display_address": ["1001 E Pike St", "Seattle, WA 98122"], "address3": "", "city": "Seattle", "state": "WA", "address2": "", "address1": "1001 E Pike St", "zip_code": "98122", "country": "US"}, "review_count": 1196, "distance": 1774.3308242719997, "display_phone": "(206) 325-7711", "price": "$$", "rating": 4.0, "phone": "+12063257711", "id": "quinns-seattle", "name": "Quinn's", "transactions": [], "url": "https://www.yelp.com/biz/quinns-seattle?adjust_creative=8_C4NSGbL05eUQksKleGYw&utm_campaign=yelp_api_v3&utm_medium=api_v3_business_search&utm_source=8_C4NSGbL05eUQksKleGYw", "is_closed": false, "image_url": "https://s3-media2.fl.yelpcdn.com/bphoto/fN8cEHmZ4ZqocvFKFzRLGg/o.jpg"}, {"coordinates": {"longitude": -122.38433, "latitude": 47.667}, "categories": [{"alias": "cocktailbars", "title": "Cocktail Bars"}, {"alias": "tapasmallplates", "title": "Tapas/Small Plates"}], "location": {"display_address": ["5335 Ballard Ave NW", "Seattle, WA 98107"], "address3": null, "city": "Seattle", "state": "WA", "address2": "", "address1": "5335 Ballard Ave NW", "zip_code": "98107", "country": "US"}, "review_count": 28, "distance": 5904.208671562, "display_phone": "(206) 268-0143", "price": "$$", "rating": 5.0, "phone": "+12062680143", "id": "little-tin-goods-and-apothocary-cabinet-seattle", "name": "Little Tin Goods & Apothocary Cabinet", "transactions": [], "url": "https://www.yelp.com/biz/little-tin-goods-and-apothocary-cabinet-seattle?adjust_creative=8_C4NSGbL05eUQksKleGYw&utm_campaign=yelp_api_v3&utm_medium=api_v3_business_search&utm_source=8_C4NSGbL05eUQksKleGYw", "is_closed": false, "image_url": "https://s3-media4.fl.yelpcdn.com/bphoto/R_6J8eq4qAGNDqpMABp5Rw/o.jpg"}, {"coordinates": {"longitude": -122.3321, "latitude": 47.60324}, "categories": [{"alias": "southern", "title": "Southern"}, {"alias": "breakfast_brunch", "title": "Breakfast & Brunch"}], "location": {"display_address": ["621 3rd Ave", "Seattle, WA 98104"], "address3": "", "city": "Seattle", "state": "WA", "address2": "", "address1": "621 3rd Ave", "zip_code": "98104", "country": "US"}, "review_count": 159, "distance": 2475.989063014, "display_phone": "(206) 623-1859", "price": "$", "rating": 4.5, "phone": "+12066231859", "id": "biscuit-bitch-seattle-5", "name": "Biscuit Bitch", "transactions": [], "url": "https://www.yelp.com/biz/biscuit-bitch-seattle-5?adjust_creative=8_C4NSGbL05eUQksKleGYw&utm_campaign=yelp_api_v3&utm_medium=api_v3_business_search&utm_source=8_C4NSGbL05eUQksKleGYw", "is_closed": false, "image_url": "https://s3-media1.fl.yelpcdn.com/bphoto/zf7xwbeJVO7erkn5XK4j8g/o.jpg"}, {"coordinates": {"longitude": -122.325373826984, "latitude": 47.6756628321622}, "categories": [{"alias": "breakfast_brunch", "title": "Breakfast & Brunch"}], "location": {"display_address": ["6412 Latona Ave NE", "Seattle, WA 98115"], "address3": "", "city": "Seattle", "state": "WA", "address2": null, "address1": "6412 Latona Ave NE", "zip_code": "98115", "country": "US"}, "review_count": 290, "distance": 5638.192977195999, "display_phone": "(206) 414-3100", "price": "$$", "rating": 4.5, "phone": "+12064143100", "id": "the-butcher-and-the-baker-seattle", "name": "The Butcher & The Baker", "transactions": [], "url": "https://www.yelp.com/biz/the-butcher-and-the-baker-seattle?adjust_creative=8_C4NSGbL05eUQksKleGYw&utm_campaign=yelp_api_v3&utm_medium=api_v3_business_search&utm_source=8_C4NSGbL05eUQksKleGYw", "is_closed": false, "image_url": "https://s3-media1.fl.yelpcdn.com/bphoto/DCyaW9oZBuHqFk01Qn9xZg/o.jpg"}, {"coordinates": {"longitude": -122.3219651, "latitude": 47.6135201}, "categories": [{"alias": "ramen", "title": "Ramen"}, {"alias": "noodles", "title": "Noodles"}], "location": {"display_address": ["1416 Harvard Ave", "Seattle, WA 98122"], "address3": "", "city": "Seattle", "state": "WA", "address2": null, "address1": "1416 Harvard Ave", "zip_code": "98122", "country": "US"}, "review_count": 114, "distance": 1664.754565154, "display_phone": "(206) 568-7669", "price": "$$", "rating": 4.0, "phone": "+12065687669", "id": "ooink-seattle", "name": "Ooink", "transactions": [], "url": "https://www.yelp.com/biz/ooink-seattle?adjust_creative=8_C4NSGbL05eUQksKleGYw&utm_campaign=yelp_api_v3&utm_medium=api_v3_business_search&utm_source=8_C4NSGbL05eUQksKleGYw", "is_closed": false, "image_url": "https://s3-media1.fl.yelpcdn.com/bphoto/r8bKsIReDLTuMChNJroSWw/o.jpg"}, {"coordinates": {"longitude": -122.349617, "latitude": 47.615562}, "categories": [{"alias": "newamerican", "title": "American (New)"}, {"alias": "gastropubs", "title": "Gastropubs"}, {"alias": "tapasmallplates", "title": "Tapas/Small Plates"}], "location": {"display_address": ["2600 1st Ave", "Seattle, WA 98121"], "address3": "", "city": "Seattle", "state": "WA", "address2": "", "address1": "2600 1st Ave", "zip_code": "98121", "country": "US"}, "review_count": 945, "distance": 1524.9824849236, "display_phone": "(206) 441-1500", "price": "$$", "rating": 4.0, "phone": "+12064411500", "id": "black-bottle-seattle-2", "name": "Black Bottle", "transactions": [], "url": "https://www.yelp.com/biz/black-bottle-seattle-2?adjust_creative=8_C4NSGbL05eUQksKleGYw&utm_campaign=yelp_api_v3&utm_medium=api_v3_business_search&utm_source=8_C4NSGbL05eUQksKleGYw", "is_closed": false, "image_url": "https://s3-media1.fl.yelpcdn.com/bphoto/lOTDfwDSlkKua6b5VtXLJg/o.jpg"}, {"coordinates": {"longitude": -122.33707331121, "latitude": 47.622183188796}, "categories": [{"alias": "burgers", "title": "Burgers"}, {"alias": "pubs", "title": "Pubs"}], "location": {"display_address": ["404 Terry Avenue North", "Seattle, WA 98109"], "address3": "", "city": "Seattle", "state": "WA", "address2": null, "address1": "404 Terry Avenue North", "zip_code": "98109", "country": "US"}, "review_count": 134, "distance": 389.46229167499996, "display_phone": "(206) 257-1888", "price": "$$", "rating": 4.0, "phone": "+12062571888", "id": "local-public-eatery-seattle", "name": "LOCAL Public Eatery", "transactions": [], "url": "https://www.yelp.com/biz/local-public-eatery-seattle?adjust_creative=8_C4NSGbL05eUQksKleGYw&utm_campaign=yelp_api_v3&utm_medium=api_v3_business_search&utm_source=8_C4NSGbL05eUQksKleGYw", "is_closed": false, "image_url": "https://s3-media2.fl.yelpcdn.com/bphoto/7dEWcyvCQXvdJlMHX-q9mg/o.jpg"}, {"coordinates": {"longitude": -122.32482, "latitude": 47.59859}, "categories": [{"alias": "cantonese", "title": "Cantonese"}, {"alias": "noodles", "title": "Noodles"}], "location": {"display_address": ["418 Maynard Ave S", "Seattle, WA 98104"], "address3": "", "city": "Seattle", "state": "WA", "address2": "", "address1": "418 Maynard Ave S", "zip_code": "98104", "country": "US"}, "review_count": 768, "distance": 3084.2931898379998, "display_phone": "(206) 389-7099", "price": "$", "rating": 4.0, "phone": "+12063897099", "id": "mikes-noodle-house-seattle", "name": "Mike's Noodle House", "transactions": [], "url": "https://www.yelp.com/biz/mikes-noodle-house-seattle?adjust_creative=8_C4NSGbL05eUQksKleGYw&utm_campaign=yelp_api_v3&utm_medium=api_v3_business_search&utm_source=8_C4NSGbL05eUQksKleGYw", "is_closed": false, "image_url": "https://s3-media1.fl.yelpcdn.com/bphoto/ISz099JWV0QCHSVRQSYWPA/o.jpg"}, {"coordinates": {"longitude": -122.34609, "latitude": 47.61345}, "categories": [{"alias": "newamerican", "title": "American (New)"}, {"alias": "breakfast_brunch", "title": "Breakfast & Brunch"}, {"alias": "vegan", "title": "Vegan"}], "location": {"display_address": ["2234 1st Ave", "Seattle, WA 98121"], "address3": "", "city": "Seattle", "state": "WA", "address2": "", "address1": "2234 1st Ave", "zip_code": "98121", "country": "US"}, "review_count": 1978, "distance": 1555.010612808, "display_phone": "(206) 441-9360", "price": "$$", "rating": 4.0, "phone": "+12064419360", "id": "local-360-seattle-2", "name": "Local 360", "transactions": [], "url": "https://www.yelp.com/biz/local-360-seattle-2?adjust_creative=8_C4NSGbL05eUQksKleGYw&utm_campaign=yelp_api_v3&utm_medium=api_v3_business_search&utm_source=8_C4NSGbL05eUQksKleGYw", "is_closed": false, "image_url": "https://s3-media3.fl.yelpcdn.com/bphoto/Kr1YwS2lxvZA-NxvGl4u9Q/o.jpg"}, {"coordinates": {"longitude": -122.32681, "latitude": 47.59985}, "categories": [{"alias": "japanese", "title": "Japanese"}, {"alias": "sushi", "title": "Sushi Bars"}, {"alias": "noodles", "title": "Noodles"}], "location": {"display_address": ["515 S Main St", "Seattle, WA 98104"], "address3": "", "city": "Seattle", "state": "WA", "address2": "", "address1": "515 S Main St", "zip_code": "98104", "country": "US"}, "review_count": 608, "distance": 2916.7201795359997, "display_phone": "(206) 467-4004", "price": "$$", "rating": 4.0, "phone": "+12064674004", "id": "tsukushinbo-seattle", "name": "Tsukushinbo", "transactions": [], "url": "https://www.yelp.com/biz/tsukushinbo-seattle?adjust_creative=8_C4NSGbL05eUQksKleGYw&utm_campaign=yelp_api_v3&utm_medium=api_v3_business_search&utm_source=8_C4NSGbL05eUQksKleGYw", "is_closed": false, "image_url": "https://s3-media1.fl.yelpcdn.com/bphoto/DZ-Qsai5udTplG9e1k2r2Q/o.jpg"}, {"coordinates": {"longitude": -122.28556, "latitude": 47.55728}, "categories": [{"alias": "asianfusion", "title": "Asian Fusion"}, {"alias": "hawaiian", "title": "Hawaiian"}, {"alias": "newamerican", "title": "American (New)"}], "location": {"display_address": ["3714 S Hudson St", "Seattle, WA 98118"], "address3": "", "city": "Seattle", "state": "WA", "address2": "", "address1": "3714 S Hudson St", "zip_code": "98118", "country": "US"}, "review_count": 245, "distance": 8461.61360144, "display_phone": "(206) 420-1201", "price": "$$", "rating": 4.0, "phone": "+12064201201", "id": "super-six-seattle", "name": "Super Six", "transactions": [], "url": "https://www.yelp.com/biz/super-six-seattle?adjust_creative=8_C4NSGbL05eUQksKleGYw&utm_campaign=yelp_api_v3&utm_medium=api_v3_business_search&utm_source=8_C4NSGbL05eUQksKleGYw", "is_closed": false, "image_url": "https://s3-media2.fl.yelpcdn.com/bphoto/_3L5pfdkuNX0EtQbgChCxA/o.jpg"}, {"coordinates": {"longitude": -122.342834472656, "latitude": 47.6131858825684}, "categories": [{"alias": "newamerican", "title": "American (New)"}, {"alias": "french", "title": "French"}, {"alias": "italian", "title": "Italian"}], "location": {"display_address": ["2107 3rd Ave", "Seattle, WA 98121"], "address3": "", "city": "Seattle", "state": "WA", "address2": "", "address1": "2107 3rd Ave", "zip_code": "98121", "country": "US"}, "review_count": 199, "distance": 1467.3111744743999, "display_phone": "(206) 443-1972", "price": "$$", "rating": 4.0, "phone": "+12064431972", "id": "orfeo-seattle", "name": "Orfeo", "transactions": [], "url": "https://www.yelp.com/biz/orfeo-seattle?adjust_creative=8_C4NSGbL05eUQksKleGYw&utm_campaign=yelp_api_v3&utm_medium=api_v3_business_search&utm_source=8_C4NSGbL05eUQksKleGYw", "is_closed": false, "image_url": "https://s3-media4.fl.yelpcdn.com/bphoto/ssx7yGEHdtfyPsnFVc1-aA/o.jpg"}, {"coordinates": {"longitude": -122.346869073808, "latitude": 47.6167700829394}, "categories": [{"alias": "vietnamese", "title": "Vietnamese"}, {"alias": "burgers", "title": "Burgers"}, {"alias": "asianfusion", "title": "Asian Fusion"}], "location": {"display_address": ["2525 4th Ave", "Seattle, WA 98121"], "address3": "", "city": "Seattle", "state": "WA", "address2": "", "address1": "2525 4th Ave", "zip_code": "98121", "country": "US"}, "review_count": 141, "distance": 1284.3729905224, "display_phone": "(206) 257-1030", "price": "$$", "rating": 4.5, "phone": "+12062571030", "id": "meekong-bar-seattle-4", "name": "Meekong Bar", "transactions": [], "url": "https://www.yelp.com/biz/meekong-bar-seattle-4?adjust_creative=8_C4NSGbL05eUQksKleGYw&utm_campaign=yelp_api_v3&utm_medium=api_v3_business_search&utm_source=8_C4NSGbL05eUQksKleGYw", "is_closed": false, "image_url": "https://s3-media3.fl.yelpcdn.com/bphoto/dJofoeQLBQtfiTht-EbsIg/o.jpg"}, {"coordinates": {"longitude": -122.325672, "latitude": 47.641699}, "categories": [{"alias": "italian", "title": "Italian"}, {"alias": "spanish", "title": "Spanish"}, {"alias": "basque", "title": "Basque"}], "location": {"display_address": ["2366 Eastlake Ave E", "Ste 101", "Seattle, WA 98102"], "address3": "", "city": "Seattle", "state": "WA", "address2": "Ste 101", "address1": "2366 Eastlake Ave E", "zip_code": "98102", "country": "US"}, "review_count": 241, "distance": 1954.81862714, "display_phone": "(206) 324-3160", "price": "$$", "rating": 4.5, "phone": "+12063243160", "id": "pomodoro-seattle", "name": "Pomodoro", "transactions": [], "url": "https://www.yelp.com/biz/pomodoro-seattle?adjust_creative=8_C4NSGbL05eUQksKleGYw&utm_campaign=yelp_api_v3&utm_medium=api_v3_business_search&utm_source=8_C4NSGbL05eUQksKleGYw", "is_closed": false, "image_url": "https://s3-media1.fl.yelpcdn.com/bphoto/FWNyUO2uIOSa3dd0wIWFUA/o.jpg"}, {"coordinates": {"longitude": -122.33876, "latitude": 47.62289}, "categories": [{"alias": "newamerican", "title": "American (New)"}, {"alias": "bars", "title": "Bars"}, {"alias": "breakfast_brunch", "title": "Breakfast & Brunch"}], "location": {"display_address": ["429 Westlake Ave N", "Seattle, WA 98109"], "address3": "", "city": "Seattle", "state": "WA", "address2": "", "address1": "429 Westlake Ave N", "zip_code": "98109", "country": "US"}, "review_count": 394, "distance": 377.7847757944, "display_phone": "(206) 467-5300", "price": "$$", "rating": 4.0, "phone": "+12064675300", "id": "re-public-seattle-2", "name": "re:public", "transactions": [], "url": "https://www.yelp.com/biz/re-public-seattle-2?adjust_creative=8_C4NSGbL05eUQksKleGYw&utm_campaign=yelp_api_v3&utm_medium=api_v3_business_search&utm_source=8_C4NSGbL05eUQksKleGYw", "is_closed": false, "image_url": "https://s3-media4.fl.yelpcdn.com/bphoto/goAcPgKBGoWkm6ZYV4StuQ/o.jpg"}, {"coordinates": {"longitude": -122.340019226074, "latitude": 47.6145858764648}, "categories": [{"alias": "newamerican", "title": "American (New)"}, {"alias": "bars", "title": "Bars"}, {"alias": "desserts", "title": "Desserts"}], "location": {"display_address": ["2030 5th Ave", "Seattle, WA 98121"], "address3": "", "city": "Seattle", "state": "WA", "address2": "", "address1": "2030 5th Ave", "zip_code": "98121", "country": "US"}, "review_count": 938, "distance": 1252.248294953, "display_phone": "(206) 448-2001", "price": "$$", "rating": 4.0, "phone": "+12064482001", "id": "palace-kitchen-seattle", "name": "Palace Kitchen", "transactions": [], "url": "https://www.yelp.com/biz/palace-kitchen-seattle?adjust_creative=8_C4NSGbL05eUQksKleGYw&utm_campaign=yelp_api_v3&utm_medium=api_v3_business_search&utm_source=8_C4NSGbL05eUQksKleGYw", "is_closed": false, "image_url": "https://s3-media2.fl.yelpcdn.com/bphoto/Q-jDlhkObGgdBgjSHUSavw/o.jpg"}, {"coordinates": {"longitude": -122.38326, "latitude": 47.55994}, "categories": [{"alias": "bars", "title": "Bars"}, {"alias": "cafes", "title": "Cafes"}, {"alias": "coffee", "title": "Coffee & Tea"}], "location": {"display_address": ["4735 40th Ave SW", "Seattle, WA 98116"], "address3": null, "city": "Seattle", "state": "WA", "address2": "", "address1": "4735 40th Ave SW", "zip_code": "98116", "country": "US"}, "review_count": 54, "distance": 8068.5516185199995, "display_phone": "(206) 618-1444", "price": "$", "rating": 5.0, "phone": "+12066181444", "id": "sound-and-fog-seattle", "name": "Sound & Fog", "transactions": [], "url": "https://www.yelp.com/biz/sound-and-fog-seattle?adjust_creative=8_C4NSGbL05eUQksKleGYw&utm_campaign=yelp_api_v3&utm_medium=api_v3_business_search&utm_source=8_C4NSGbL05eUQksKleGYw", "is_closed": false, "image_url": "https://s3-media3.fl.yelpcdn.com/bphoto/O8UrEYP4ChZdUA1r6NkfLg/o.jpg"}, {"coordinates": {"longitude": -122.348531557074, "latitude": 47.6184417733982}, "categories": [{"alias": "thai", "title": "Thai"}, {"alias": "seafood", "title": "Seafood"}, {"alias": "salad", "title": "Salad"}], "location": {"display_address": ["2720 4th Ave", "Ste 116", "Seattle, WA 98121"], "address3": "", "city": "Seattle", "state": "WA", "address2": "Ste 116", "address1": "2720 4th Ave", "zip_code": "98121", "country": "US"}, "review_count": 134, "distance": 1246.836165, "display_phone": "(206) 659-0466", "price": "$$", "rating": 4.0, "phone": "+12066590466", "id": "mantra-seattle", "name": "Mantra", "transactions": ["delivery", "pickup"], "url": "https://www.yelp.com/biz/mantra-seattle?adjust_creative=8_C4NSGbL05eUQksKleGYw&utm_campaign=yelp_api_v3&utm_medium=api_v3_business_search&utm_source=8_C4NSGbL05eUQksKleGYw", "is_closed": false, "image_url": "https://s3-media1.fl.yelpcdn.com/bphoto/CEETCbFJrZW99TkzN6g0Xw/o.jpg"}, {"coordinates": {"longitude": -122.344183, "latitude": 47.654129}, "categories": [{"alias": "newamerican", "title": "American (New)"}], "location": {"display_address": ["3801 Stone Way N", "Seattle, WA 98103"], "address3": "", "city": "Seattle", "state": "WA", "address2": "", "address1": "3801 Stone Way N", "zip_code": "98103", "country": "US"}, "review_count": 482, "distance": 3257.8231721499997, "display_phone": "(206) 282-0942", "price": "$$$$", "rating": 4.5, "phone": "+12062820942", "id": "art-of-the-table-seattle", "name": "Art of The Table", "transactions": [], "url": "https://www.yelp.com/biz/art-of-the-table-seattle?adjust_creative=8_C4NSGbL05eUQksKleGYw&utm_campaign=yelp_api_v3&utm_medium=api_v3_business_search&utm_source=8_C4NSGbL05eUQksKleGYw", "is_closed": false, "image_url": "https://s3-media1.fl.yelpcdn.com/bphoto/rG3wooV8cP9DV88KM-yTyw/o.jpg"}, {"coordinates": {"longitude": -122.32528, "latitude": 47.5982}, "categories": [{"alias": "poke", "title": "Poke"}, {"alias": "hawaiian", "title": "Hawaiian"}, {"alias": "desserts", "title": "Desserts"}], "location": {"display_address": ["625 S King St", "Seattle, WA 98104"], "address3": null, "city": "Seattle", "state": "WA", "address2": "", "address1": "625 S King St", "zip_code": "98104", "country": "US"}, "review_count": 190, "distance": 3117.096367058, "display_phone": "(206) 799-9560", "price": "$$", "rating": 4.5, "phone": "+12067999560", "id": "gopok\u00e9-seattle-5", "name": "goPok\u00e9", "transactions": [], "url": "https://www.yelp.com/biz/gopok%C3%A9-seattle-5?adjust_creative=8_C4NSGbL05eUQksKleGYw&utm_campaign=yelp_api_v3&utm_medium=api_v3_business_search&utm_source=8_C4NSGbL05eUQksKleGYw", "is_closed": false, "image_url": "https://s3-media2.fl.yelpcdn.com/bphoto/pnXl4bvA2UPogt-iBOuSjw/o.jpg"}, {"coordinates": {"longitude": -122.35676, "latitude": 47.63857}, "categories": [{"alias": "mediterranean", "title": "Mediterranean"}, {"alias": "lounges", "title": "Lounges"}, {"alias": "wine_bars", "title": "Wine Bars"}], "location": {"display_address": ["2 Boston St", "Seattle, WA 98109"], "address3": "", "city": "Seattle", "state": "WA", "address2": null, "address1": "2 Boston St", "zip_code": "98109", "country": "US"}, "review_count": 94, "distance": 2156.202422436, "display_phone": "(206) 466-1027", "price": "$$", "rating": 4.0, "phone": "+12064661027", "id": "grappa-seattle", "name": "Grappa", "transactions": [], "url": "https://www.yelp.com/biz/grappa-seattle?adjust_creative=8_C4NSGbL05eUQksKleGYw&utm_campaign=yelp_api_v3&utm_medium=api_v3_business_search&utm_source=8_C4NSGbL05eUQksKleGYw", "is_closed": false, "image_url": "https://s3-media1.fl.yelpcdn.com/bphoto/YN1Z82BDbNYBp7rIKE-xEA/o.jpg"}], "region": {"center": {"longitude": -122.33551025390625, "latitude": 47.62541904760501}}, "total": 7629}