{"status": "OK", "copyright": "Copyright (c) 2017 The New York Times Company.  All Rights Reserved.", "results": [{"price": 0, "contributor": "by Arianna Huffington", "age_group": "", "contributor_note": "", "description": "Personal well-being as the indispensable third measure \u2013 with money and power -- of success.", "author": "Arianna Huffington", "ranks_history": [{"list_name": "E-Book Nonfiction", "ranks_last_week": null, "dagger": 0, "weeks_on_list": 0, "asterisk": 0, "rank": 11, "primary_isbn10": "0804140855", "published_date": "2015-12-13", "display_name": "E-Book Nonfiction", "bestsellers_date": "2015-11-28", "primary_isbn13": "9780804140850"}, {"list_name": "Paperback Nonfiction", "ranks_last_week": null, "dagger": 0, "weeks_on_list": 0, "asterisk": 0, "rank": 11, "primary_isbn10": "0804140863", "published_date": "2015-04-26", "display_name": "Paperback Nonfiction", "bestsellers_date": "2015-04-11", "primary_isbn13": "9780804140867"}, {"list_name": "Paperback Nonfiction", "ranks_last_week": null, "dagger": 0, "weeks_on_list": 0, "asterisk": 0, "rank": 13, "primary_isbn10": "0804140863", "published_date": "2015-04-19", "display_name": "Paperback Nonfiction", "bestsellers_date": "2015-04-04", "primary_isbn13": "9780804140867"}, {"list_name": "Business Books", "ranks_last_week": null, "dagger": 0, "weeks_on_list": 0, "asterisk": 0, "rank": 7, "primary_isbn10": "0804140863", "published_date": "2015-04-12", "display_name": "Business", "bestsellers_date": "2015-03-28", "primary_isbn13": "9780804140867"}, {"list_name": "Paperback Nonfiction", "ranks_last_week": null, "dagger": 0, "weeks_on_list": 2, "asterisk": 0, "rank": 7, "primary_isbn10": "0804140863", "published_date": "2015-04-12", "display_name": "Paperback Nonfiction", "bestsellers_date": "2015-03-28", "primary_isbn13": "9780804140867"}, {"list_name": "Paperback Nonfiction", "ranks_last_week": null, "dagger": 0, "weeks_on_list": 1, "asterisk": 0, "rank": 5, "primary_isbn10": "0804140863", "published_date": "2015-04-05", "display_name": "Paperback Nonfiction", "bestsellers_date": "2015-03-21", "primary_isbn13": "9780804140867"}, {"list_name": "Combined Print and E-Book Nonfiction", "ranks_last_week": null, "dagger": 0, "weeks_on_list": 9, "asterisk": 0, "rank": 9, "primary_isbn10": "0804140863", "published_date": "2015-04-05", "display_name": "Combined Print & E-Book Nonfiction", "bestsellers_date": "2015-03-21", "primary_isbn13": "9780804140867"}, {"list_name": "Hardcover Nonfiction", "ranks_last_week": null, "dagger": 0, "weeks_on_list": 0, "asterisk": 0, "rank": 22, "primary_isbn10": "0804140847", "published_date": "2014-09-14", "display_name": "Hardcover Nonfiction", "bestsellers_date": "2014-08-30", "primary_isbn13": "9780804140843"}, {"list_name": "Hardcover Nonfiction", "ranks_last_week": null, "dagger": 0, "weeks_on_list": 0, "asterisk": 0, "rank": 19, "primary_isbn10": "0804140847", "published_date": "2014-08-10", "display_name": "Hardcover Nonfiction", "bestsellers_date": "2014-07-26", "primary_isbn13": "9780804140843"}, {"list_name": "Hardcover Nonfiction", "ranks_last_week": null, "dagger": 0, "weeks_on_list": 0, "asterisk": 0, "rank": 24, "primary_isbn10": "0804140847", "published_date": "2014-08-03", "display_name": "Hardcover Nonfiction", "bestsellers_date": "2014-07-19", "primary_isbn13": "9780804140843"}, {"list_name": "Hardcover Nonfiction", "ranks_last_week": null, "dagger": 0, "weeks_on_list": 11, "asterisk": 0, "rank": 14, "primary_isbn10": "0804140847", "published_date": "2014-07-27", "display_name": "Hardcover Nonfiction", "bestsellers_date": "2014-07-12", "primary_isbn13": "9780804140843"}, {"list_name": "Hardcover Nonfiction", "ranks_last_week": null, "dagger": 0, "weeks_on_list": 0, "asterisk": 0, "rank": 22, "primary_isbn10": "0804140847", "published_date": "2014-07-20", "display_name": "Hardcover Nonfiction", "bestsellers_date": "2014-07-05", "primary_isbn13": "9780804140843"}, {"list_name": "Business Books", "ranks_last_week": null, "dagger": 0, "weeks_on_list": 0, "asterisk": 1, "rank": 10, "primary_isbn10": "0804140847", "published_date": "2014-07-13", "display_name": "Business", "bestsellers_date": "2014-06-28", "primary_isbn13": "9780804140843"}, {"list_name": "Hardcover Nonfiction", "ranks_last_week": null, "dagger": 0, "weeks_on_list": 0, "asterisk": 0, "rank": 16, "primary_isbn10": "0804140847", "published_date": "2014-07-13", "display_name": "Hardcover Nonfiction", "bestsellers_date": "2014-06-28", "primary_isbn13": "9780804140843"}, {"list_name": "Hardcover Nonfiction", "ranks_last_week": null, "dagger": 0, "weeks_on_list": 0, "asterisk": 0, "rank": 22, "primary_isbn10": "0804140847", "published_date": "2014-07-06", "display_name": "Hardcover Nonfiction", "bestsellers_date": "2014-06-21", "primary_isbn13": "9780804140843"}, {"list_name": "Business Books", "ranks_last_week": null, "dagger": 0, "weeks_on_list": 0, "asterisk": 1, "rank": 10, "primary_isbn10": "0804140847", "published_date": "2014-07-06", "display_name": "Business", "bestsellers_date": "2014-06-28", "primary_isbn13": "9780804140843"}, {"list_name": "Hardcover Nonfiction", "ranks_last_week": null, "dagger": 0, "weeks_on_list": 0, "asterisk": 0, "rank": 23, "primary_isbn10": "0804140847", "published_date": "2014-06-29", "display_name": "Hardcover Nonfiction", "bestsellers_date": "2014-06-14", "primary_isbn13": "9780804140843"}, {"list_name": "Hardcover Nonfiction", "ranks_last_week": null, "dagger": 0, "weeks_on_list": 0, "asterisk": 0, "rank": 17, "primary_isbn10": "0804140847", "published_date": "2014-06-22", "display_name": "Hardcover Nonfiction", "bestsellers_date": "2014-06-07", "primary_isbn13": "9780804140843"}, {"list_name": "Hardcover Nonfiction", "ranks_last_week": null, "dagger": 0, "weeks_on_list": 10, "asterisk": 0, "rank": 12, "primary_isbn10": "0804140847", "published_date": "2014-06-15", "display_name": "Hardcover Nonfiction", "bestsellers_date": "2014-05-31", "primary_isbn13": "9780804140843"}, {"list_name": "Business Books", "ranks_last_week": null, "dagger": 0, "weeks_on_list": 0, "asterisk": 0, "rank": 7, "primary_isbn10": "0804140847", "published_date": "2014-06-08", "display_name": "Business", "bestsellers_date": "2014-05-24", "primary_isbn13": "9780804140843"}], "reviews": [{"article_chapter_link": "", "sunday_review_link": "", "book_review_link": "", "first_chapter_link": ""}], "title": "THRIVE", "isbns": [{"isbn10": "0804140847", "isbn13": "9780804140843"}, {"isbn10": "0804140855", "isbn13": "9780804140850"}, {"isbn10": "0804140863", "isbn13": "9780804140867"}], "publisher": "Harmony"}], "num_results": 1}