{"total": 29572, "region": {"center": {"latitude": 34.0615895441259, "longitude": -118.32138061523438}}, "businesses": [{"review_count": 732, "distance": 5025.188611968, "coordinates": {"latitude": 34.0838186238941, "longitude": -118.273877169312}, "is_closed": false, "name": "Local", "price": "$$", "url": "https://www.yelp.com/biz/local-los-angeles?adjust_creative=8_C4NSGbL05eUQksKleGYw&utm_campaign=yelp_api_v3&utm_medium=api_v3_business_search&utm_source=8_C4NSGbL05eUQksKleGYw", "transactions": [], "rating": 4.0, "display_phone": "(323) 662-4740", "categories": [{"alias": "salad", "title": "Salad"}, {"alias": "breakfast_brunch", "title": "Breakfast & Brunch"}], "id": "local-los-angeles", "phone": "+13236624740", "image_url": "https://s3-media3.fl.yelpcdn.com/bphoto/YR-190Pgsee488Jm-o5k3A/o.jpg", "location": {"state": "CA", "address1": "2943 W Sunset Blvd", "display_address": ["2943 W Sunset Blvd", "Los Angeles, CA 90026"], "city": "Los Angeles", "address2": "", "address3": "", "country": "US", "zip_code": "90026"}}, {"review_count": 18, "distance": 18497.37898378, "coordinates": {"latitude": 33.9228208765226, "longitude": -118.432030119002}, "is_closed": false, "name": "El Segundo Beach Cafe", "price": "$$", "url": "https://www.yelp.com/biz/el-segundo-beach-cafe-los-angeles?adjust_creative=8_C4NSGbL05eUQksKleGYw&utm_campaign=yelp_api_v3&utm_medium=api_v3_business_search&utm_source=8_C4NSGbL05eUQksKleGYw", "transactions": [], "rating": 4.5, "display_phone": "(310) 283-0071", "categories": [{"alias": "cafes", "title": "Cafes"}, {"alias": "hotdog", "title": "Hot Dogs"}, {"alias": "breakfast_brunch", "title": "Breakfast & Brunch"}], "id": "el-segundo-beach-cafe-los-angeles", "phone": "+13102830071", "image_url": "https://s3-media3.fl.yelpcdn.com/bphoto/kNm-asqvPgipOW27dLdw1g/o.jpg", "location": {"state": "CA", "address1": "12501 Vista Del Mar", "display_address": ["12501 Vista Del Mar", "Los Angeles, CA 90293"], "city": "Los Angeles", "address2": "", "address3": "", "country": "US", "zip_code": "90293"}}, {"review_count": 395, "distance": 9287.723228919998, "coordinates": {"latitude": 34.0257854, "longitude": -118.4124537}, "is_closed": false, "name": "The Doughroom", "price": "$$", "url": "https://www.yelp.com/biz/the-doughroom-los-angeles?adjust_creative=8_C4NSGbL05eUQksKleGYw&utm_campaign=yelp_api_v3&utm_medium=api_v3_business_search&utm_source=8_C4NSGbL05eUQksKleGYw", "transactions": ["pickup"], "rating": 4.0, "display_phone": "(424) 258-6194", "categories": [{"alias": "newamerican", "title": "American (New)"}, {"alias": "italian", "title": "Italian"}, {"alias": "pizza", "title": "Pizza"}], "id": "the-doughroom-los-angeles", "phone": "+14242586194", "image_url": "https://s3-media2.fl.yelpcdn.com/bphoto/GKdXPKgFTdtvvTZ0-3WRZQ/o.jpg", "location": {"state": "CA", "address1": "3409 Overland Ave", "display_address": ["3409 Overland Ave", "Los Angeles, CA 90034"], "city": "Los Angeles", "address2": "", "address3": "", "country": "US", "zip_code": "90034"}}, {"review_count": 1376, "distance": 5533.452623843999, "coordinates": {"latitude": 34.0438418185227, "longitude": -118.265265785158}, "is_closed": false, "name": "Tom's Urban", "price": "$$", "url": "https://www.yelp.com/biz/toms-urban-los-angeles?adjust_creative=8_C4NSGbL05eUQksKleGYw&utm_campaign=yelp_api_v3&utm_medium=api_v3_business_search&utm_source=8_C4NSGbL05eUQksKleGYw", "transactions": [], "rating": 3.0, "display_phone": "(213) 746-8667", "categories": [{"alias": "newamerican", "title": "American (New)"}, {"alias": "sportsbars", "title": "Sports Bars"}, {"alias": "gastropubs", "title": "Gastropubs"}], "id": "toms-urban-los-angeles", "phone": "+12137468667", "image_url": "https://s3-media1.fl.yelpcdn.com/bphoto/c8U5nDeDjR8Czzg9t2SKFg/o.jpg", "location": {"state": "CA", "address1": "1011 S Figueroa St", "display_address": ["1011 S Figueroa St", "Ste B 101", "Los Angeles, CA 90015"], "city": "Los Angeles", "address2": "Ste B 101", "address3": "", "country": "US", "zip_code": "90015"}}, {"review_count": 455, "distance": 2221.396463968, "coordinates": {"latitude": 34.07888, "longitude": -118.30937}, "is_closed": false, "name": "Western Doma Noodles", "price": "$", "url": "https://www.yelp.com/biz/western-doma-noodles-los-angeles?adjust_creative=8_C4NSGbL05eUQksKleGYw&utm_campaign=yelp_api_v3&utm_medium=api_v3_business_search&utm_source=8_C4NSGbL05eUQksKleGYw", "transactions": [], "rating": 4.0, "display_phone": "(323) 871-1955", "categories": [{"alias": "korean", "title": "Korean"}, {"alias": "noodles", "title": "Noodles"}], "id": "western-doma-noodles-los-angeles", "phone": "+13238711955", "image_url": "https://s3-media2.fl.yelpcdn.com/bphoto/9TQ2_cr4ZHd7PN1ujLtZTw/o.jpg", "location": {"state": "CA", "address1": "429 N Western Ave", "display_address": ["429 N Western Ave", "Ste 10", "Los Angeles, CA 90004"], "city": "Los Angeles", "address2": "Ste 10", "address3": "", "country": "US", "zip_code": "90004"}}, {"review_count": 159, "distance": 3447.2941499639996, "coordinates": {"latitude": 34.083708, "longitude": -118.295155}, "is_closed": false, "name": "Gracie's Pizza", "price": "$", "url": "https://www.yelp.com/biz/gracies-pizza-los-angeles?adjust_creative=8_C4NSGbL05eUQksKleGYw&utm_campaign=yelp_api_v3&utm_medium=api_v3_business_search&utm_source=8_C4NSGbL05eUQksKleGYw", "transactions": [], "rating": 5.0, "display_phone": "(323) 663-1219", "categories": [{"alias": "pizza", "title": "Pizza"}, {"alias": "italian", "title": "Italian"}, {"alias": "bars", "title": "Bars"}], "id": "gracies-pizza-los-angeles", "phone": "+13236631219", "image_url": "https://s3-media3.fl.yelpcdn.com/bphoto/3l_SYaf8Oo3QIgp4Rb7qNg/o.jpg", "location": {"state": "CA", "address1": "4330 Melrose Ave", "display_address": ["4330 Melrose Ave", "Los Angeles, CA 90029"], "city": "Los Angeles", "address2": "", "address3": null, "country": "US", "zip_code": "90029"}}, {"review_count": 6, "distance": 4623.208471438, "coordinates": {"latitude": 34.1021807911954, "longitude": -118.332244567573}, "is_closed": false, "name": "Crying Tiger", "price": "$$", "url": "https://www.yelp.com/biz/crying-tiger-los-angeles?adjust_creative=8_C4NSGbL05eUQksKleGYw&utm_campaign=yelp_api_v3&utm_medium=api_v3_business_search&utm_source=8_C4NSGbL05eUQksKleGYw", "transactions": [], "rating": 4.5, "display_phone": "(323) 461-1464", "categories": [{"alias": "thai", "title": "Thai"}, {"alias": "noodles", "title": "Noodles"}], "id": "crying-tiger-los-angeles", "phone": "+13234611464", "image_url": "https://s3-media1.fl.yelpcdn.com/bphoto/pJcu77zjtsk0xy4bel7o0A/o.jpg", "location": {"state": "CA", "address1": "1721 N Hudson Ave", "display_address": ["1721 N Hudson Ave", "Los Angeles, CA 90028"], "city": "Los Angeles", "address2": "", "address3": null, "country": "US", "zip_code": "90028"}}, {"review_count": 93, "distance": 9705.978946738, "coordinates": {"latitude": 34.0754221, "longitude": -118.2173365}, "is_closed": false, "name": "Boda Restaurant", "price": "$", "url": "https://www.yelp.com/biz/boda-restaurant-los-angeles?adjust_creative=8_C4NSGbL05eUQksKleGYw&utm_campaign=yelp_api_v3&utm_medium=api_v3_business_search&utm_source=8_C4NSGbL05eUQksKleGYw", "transactions": [], "rating": 4.0, "display_phone": "(323) 227-8573", "categories": [{"alias": "vietnamese", "title": "Vietnamese"}, {"alias": "chinese", "title": "Chinese"}], "id": "boda-restaurant-los-angeles", "phone": "+13232278573", "image_url": "https://s3-media1.fl.yelpcdn.com/bphoto/ebWcgQAZxrQIXUPQW589tg/o.jpg", "location": {"state": "CA", "address1": "2310 Pasadena Ave", "display_address": ["2310 Pasadena Ave", "Los Angeles, CA 90031"], "city": "Los Angeles", "address2": "", "address3": "", "country": "US", "zip_code": "90031"}}, {"review_count": 201, "distance": 5485.400467322, "coordinates": {"latitude": 34.1042113, "longitude": -118.2916451}, "is_closed": false, "name": "Good Greek Grill", "price": "$", "url": "https://www.yelp.com/biz/good-greek-grill-los-angeles?adjust_creative=8_C4NSGbL05eUQksKleGYw&utm_campaign=yelp_api_v3&utm_medium=api_v3_business_search&utm_source=8_C4NSGbL05eUQksKleGYw", "transactions": ["delivery", "pickup"], "rating": 4.5, "display_phone": "(323) 326-7228", "categories": [{"alias": "greek", "title": "Greek"}], "id": "good-greek-grill-los-angeles", "phone": "+13233267228", "image_url": "https://s3-media1.fl.yelpcdn.com/bphoto/R4vb0pdSTzR3WXHcXEXoLg/o.jpg", "location": {"state": "CA", "address1": "1820 N Vermont Ave", "display_address": ["1820 N Vermont Ave", "Los Angeles, CA 90027"], "city": "Los Angeles", "address2": null, "address3": "", "country": "US", "zip_code": "90027"}}, {"review_count": 134, "distance": 5488.545117682, "coordinates": {"latitude": 34.02196, "longitude": -118.28002}, "is_closed": false, "name": "Amazebowls", "price": "$", "url": "https://www.yelp.com/biz/amazebowls-los-angeles-2?adjust_creative=8_C4NSGbL05eUQksKleGYw&utm_campaign=yelp_api_v3&utm_medium=api_v3_business_search&utm_source=8_C4NSGbL05eUQksKleGYw", "transactions": [], "rating": 4.5, "display_phone": "(310) 384-2202", "categories": [{"alias": "foodtrucks", "title": "Food Trucks"}, {"alias": "vegan", "title": "Vegan"}, {"alias": "gluten_free", "title": "Gluten-Free"}], "id": "amazebowls-los-angeles-2", "phone": "+13103842202", "image_url": "https://s3-media3.fl.yelpcdn.com/bphoto/wknH4OxCD3Or62j0BGtIOA/o.jpg", "location": {"state": "CA", "address1": "Jefferson Hoover", "display_address": ["Jefferson Hoover", "Los Angeles, CA 90007"], "city": "Los Angeles", "address2": null, "address3": "", "country": "US", "zip_code": "90007"}}, {"review_count": 1147, "distance": 11210.78635918, "coordinates": {"latitude": 34.059847396901, "longitude": -118.44306252304}, "is_closed": false, "name": "Palomino", "price": "$$", "url": "https://www.yelp.com/biz/palomino-los-angeles?adjust_creative=8_C4NSGbL05eUQksKleGYw&utm_campaign=yelp_api_v3&utm_medium=api_v3_business_search&utm_source=8_C4NSGbL05eUQksKleGYw", "transactions": ["delivery"], "rating": 3.5, "display_phone": "(310) 208-1960", "categories": [{"alias": "newamerican", "title": "American (New)"}, {"alias": "mediterranean", "title": "Mediterranean"}], "id": "palomino-los-angeles", "phone": "+13102081960", "image_url": "https://s3-media2.fl.yelpcdn.com/bphoto/EO60dz89qLCx0ov_ORq5iA/o.jpg", "location": {"state": "CA", "address1": "10877 Wilshire Blvd", "display_address": ["10877 Wilshire Blvd", "Los Angeles, CA 90024"], "city": "Los Angeles", "address2": "", "address3": "", "country": "US", "zip_code": "90024"}}, {"review_count": 191, "distance": 8576.80130727, "coordinates": {"latitude": 34.0579684054181, "longitude": -118.414382588885}, "is_closed": false, "name": "The Stand", "price": "$$", "url": "https://www.yelp.com/biz/the-stand-los-angeles-6?adjust_creative=8_C4NSGbL05eUQksKleGYw&utm_campaign=yelp_api_v3&utm_medium=api_v3_business_search&utm_source=8_C4NSGbL05eUQksKleGYw", "transactions": ["pickup"], "rating": 4.0, "display_phone": "(310) 785-0400", "categories": [{"alias": "newamerican", "title": "American (New)"}, {"alias": "burgers", "title": "Burgers"}], "id": "the-stand-los-angeles-6", "phone": "+13107850400", "image_url": "https://s3-media4.fl.yelpcdn.com/bphoto/kdr_Lzk7IYrQ8cD3f52GJw/o.jpg", "location": {"state": "CA", "address1": "2000 Ave of the Stars", "display_address": ["2000 Ave of the Stars", "Los Angeles, CA 90067"], "city": "Los Angeles", "address2": "", "address3": "", "country": "US", "zip_code": "90067"}}, {"review_count": 609, "distance": 5521.296796021999, "coordinates": {"latitude": 34.102568, "longitude": -118.287531}, "is_closed": false, "name": "Spitz - Los Feliz", "price": "$$", "url": "https://www.yelp.com/biz/spitz-los-feliz-los-angeles-2?adjust_creative=8_C4NSGbL05eUQksKleGYw&utm_campaign=yelp_api_v3&utm_medium=api_v3_business_search&utm_source=8_C4NSGbL05eUQksKleGYw", "transactions": ["delivery", "pickup"], "rating": 4.0, "display_phone": "(323) 522-3309", "categories": [{"alias": "bars", "title": "Bars"}, {"alias": "sandwiches", "title": "Sandwiches"}, {"alias": "mediterranean", "title": "Mediterranean"}], "id": "spitz-los-feliz-los-angeles-2", "phone": "+13235223309", "image_url": "https://s3-media2.fl.yelpcdn.com/bphoto/iosOOaScaoS-cbiCe9xoVQ/o.jpg", "location": {"state": "CA", "address1": "1725 Hillhurst Ave", "display_address": ["1725 Hillhurst Ave", "Los Angeles, CA 90027"], "city": "Los Angeles", "address2": "", "address3": "", "country": "US", "zip_code": "90027"}}, {"review_count": 1268, "distance": 7593.00774192, "coordinates": {"latitude": 34.0489331738058, "longitude": -118.240384097623}, "is_closed": false, "name": "Shabu Shabu House", "price": "$$", "url": "https://www.yelp.com/biz/shabu-shabu-house-los-angeles?adjust_creative=8_C4NSGbL05eUQksKleGYw&utm_campaign=yelp_api_v3&utm_medium=api_v3_business_search&utm_source=8_C4NSGbL05eUQksKleGYw", "transactions": [], "rating": 4.0, "display_phone": "(213) 680-3890", "categories": [{"alias": "japanese", "title": "Japanese"}, {"alias": "hotpot", "title": "Hot Pot"}], "id": "shabu-shabu-house-los-angeles", "phone": "+12136803890", "image_url": "https://s3-media1.fl.yelpcdn.com/bphoto/2LfsWgQSX8P0JUEiFSuULA/o.jpg", "location": {"state": "CA", "address1": "127 Japanese Village Plaza Mall", "display_address": ["127 Japanese Village Plaza Mall", "Los Angeles, CA 90012"], "city": "Los Angeles", "address2": "", "address3": "", "country": "US", "zip_code": "90012"}}, {"review_count": 1309, "distance": 5966.019719479999, "coordinates": {"latitude": 34.051017473398, "longitude": -118.257885974904}, "is_closed": false, "name": "DRAGO Centro", "price": "$$$", "url": "https://www.yelp.com/biz/drago-centro-los-angeles?adjust_creative=8_C4NSGbL05eUQksKleGYw&utm_campaign=yelp_api_v3&utm_medium=api_v3_business_search&utm_source=8_C4NSGbL05eUQksKleGYw", "transactions": [], "rating": 3.5, "display_phone": "(213) 228-8998", "categories": [{"alias": "italian", "title": "Italian"}], "id": "drago-centro-los-angeles", "phone": "+12132288998", "image_url": "https://s3-media4.fl.yelpcdn.com/bphoto/N8wP6NVCktCUsI1zl_2vEQ/o.jpg", "location": {"state": "CA", "address1": "525 S Flower St", "display_address": ["525 S Flower St", "Ste 120", "Los Angeles, CA 90071"], "city": "Los Angeles", "address2": "Ste 120", "address3": "", "country": "US", "zip_code": "90071"}}, {"review_count": 185, "distance": 4561.34592464, "coordinates": {"latitude": 34.1018677813075, "longitude": -118.312002611182}, "is_closed": false, "name": "Catch 56", "price": "$$", "url": "https://www.yelp.com/biz/catch-56-los-angeles?adjust_creative=8_C4NSGbL05eUQksKleGYw&utm_campaign=yelp_api_v3&utm_medium=api_v3_business_search&utm_source=8_C4NSGbL05eUQksKleGYw", "transactions": ["delivery", "pickup"], "rating": 4.5, "display_phone": "(323) 667-2777", "categories": [{"alias": "seafood", "title": "Seafood"}, {"alias": "british", "title": "British"}, {"alias": "fishnchips", "title": "Fish & Chips"}], "id": "catch-56-los-angeles", "phone": "+13236672777", "image_url": "https://s3-media4.fl.yelpcdn.com/bphoto/ZGOlIbCWagr63bHiTlgFTw/o.jpg", "location": {"state": "CA", "address1": "5615 Hollywood Blvd", "display_address": ["5615 Hollywood Blvd", "Los Angeles, CA 90028"], "city": "Los Angeles", "address2": null, "address3": "", "country": "US", "zip_code": "90028"}}, {"review_count": 319, "distance": 1104.03781746, "coordinates": {"latitude": 34.06273, "longitude": -118.30946}, "is_closed": false, "name": "Klat", "price": "$$", "url": "https://www.yelp.com/biz/klat-los-angeles?adjust_creative=8_C4NSGbL05eUQksKleGYw&utm_campaign=yelp_api_v3&utm_medium=api_v3_business_search&utm_source=8_C4NSGbL05eUQksKleGYw", "transactions": [], "rating": 4.0, "display_phone": "(213) 674-7776", "categories": [{"alias": "cafes", "title": "Cafes"}, {"alias": "coffee", "title": "Coffee & Tea"}, {"alias": "breakfast_brunch", "title": "Breakfast & Brunch"}], "id": "klat-los-angeles", "phone": "+12136747776", "image_url": "https://s3-media2.fl.yelpcdn.com/bphoto/PpwqTzQEg8IaSUwQsOZaew/o.jpg", "location": {"state": "CA", "address1": "621 S Western Ave", "display_address": ["621 S Western Ave", "Ste 101", "Los Angeles, CA 90005"], "city": "Los Angeles", "address2": "Ste 101", "address3": "", "country": "US", "zip_code": "90005"}}, {"review_count": 181, "distance": 11999.9310562, "coordinates": {"latitude": 34.0342597, "longitude": -118.4475145}, "is_closed": false, "name": "Yamakase", "price": "$$$$", "url": "https://www.yelp.com/biz/yamakase-los-angeles?adjust_creative=8_C4NSGbL05eUQksKleGYw&utm_campaign=yelp_api_v3&utm_medium=api_v3_business_search&utm_source=8_C4NSGbL05eUQksKleGYw", "transactions": [], "rating": 4.5, "display_phone": "", "categories": [{"alias": "japanese", "title": "Japanese"}, {"alias": "sushi", "title": "Sushi Bars"}], "id": "yamakase-los-angeles", "phone": "", "image_url": "https://s3-media1.fl.yelpcdn.com/bphoto/g0LVe8RzKLv3DUX-a5xqew/o.jpg", "location": {"state": "CA", "address1": "11678 W Olympic Blvd", "display_address": ["11678 W Olympic Blvd", "Los Angeles, CA 90064"], "city": "Los Angeles", "address2": "", "address3": "", "country": "US", "zip_code": "90064"}}, {"review_count": 231, "distance": 11610.10545602, "coordinates": {"latitude": 34.124659363344, "longitude": -118.220903921706}, "is_closed": false, "name": "Crawfish On Fire", "price": "$$", "url": "https://www.yelp.com/biz/crawfish-on-fire-los-angeles-7?adjust_creative=8_C4NSGbL05eUQksKleGYw&utm_campaign=yelp_api_v3&utm_medium=api_v3_business_search&utm_source=8_C4NSGbL05eUQksKleGYw", "transactions": ["pickup"], "rating": 4.0, "display_phone": "(323) 675-1050", "categories": [{"alias": "cajun", "title": "Cajun/Creole"}, {"alias": "seafood", "title": "Seafood"}, {"alias": "fishnchips", "title": "Fish & Chips"}], "id": "crawfish-on-fire-los-angeles-7", "phone": "+13236751050", "image_url": "https://s3-media3.fl.yelpcdn.com/bphoto/VGODtc0nyVSfPpCT9WpqGQ/o.jpg", "location": {"state": "CA", "address1": "4411 Eagle Rock Blvd", "display_address": ["4411 Eagle Rock Blvd", "Los Angeles, CA 90041"], "city": "Los Angeles", "address2": null, "address3": "", "country": "US", "zip_code": "90041"}}, {"review_count": 654, "distance": 5804.219894559999, "coordinates": {"latitude": 34.0470161437988, "longitude": -118.260833740234}, "is_closed": false, "name": "Orchid Bar|Kitchen", "price": "$$", "url": "https://www.yelp.com/biz/orchid-bar-kitchen-los-angeles-3?adjust_creative=8_C4NSGbL05eUQksKleGYw&utm_campaign=yelp_api_v3&utm_medium=api_v3_business_search&utm_source=8_C4NSGbL05eUQksKleGYw", "transactions": [], "rating": 4.0, "display_phone": "(213) 784-3048", "categories": [{"alias": "newamerican", "title": "American (New)"}, {"alias": "cocktailbars", "title": "Cocktail Bars"}], "id": "orchid-bar-kitchen-los-angeles-3", "phone": "+12137843048", "image_url": "https://s3-media3.fl.yelpcdn.com/bphoto/DXd9fnI2PoXFbfv3li7GTg/o.jpg", "location": {"state": "CA", "address1": "819 S Flower St", "display_address": ["819 S Flower St", "Los Angeles, CA 90017"], "city": "Los Angeles", "address2": "", "address3": "", "country": "US", "zip_code": "90017"}}, {"review_count": 249, "distance": 8842.77290572, "coordinates": {"latitude": 34.1157446801662, "longitude": -118.25143866241}, "is_closed": false, "name": "Momed Atwater Village", "price": "$$", "url": "https://www.yelp.com/biz/momed-atwater-village-los-angeles-2?adjust_creative=8_C4NSGbL05eUQksKleGYw&utm_campaign=yelp_api_v3&utm_medium=api_v3_business_search&utm_source=8_C4NSGbL05eUQksKleGYw", "transactions": ["pickup"], "rating": 4.0, "display_phone": "(323) 522-3488", "categories": [{"alias": "mediterranean", "title": "Mediterranean"}, {"alias": "vegetarian", "title": "Vegetarian"}, {"alias": "cocktailbars", "title": "Cocktail Bars"}], "id": "momed-atwater-village-los-angeles-2", "phone": "+13235223488", "image_url": "https://s3-media2.fl.yelpcdn.com/bphoto/UbQWxZc77MET2vwizgk-5A/o.jpg", "location": {"state": "CA", "address1": "3245 Casitas Ave", "display_address": ["3245 Casitas Ave", "Ste 120", "Los Angeles, CA 90039"], "city": "Los Angeles", "address2": "Ste 120", "address3": "", "country": "US", "zip_code": "90039"}}, {"review_count": 28, "distance": 13680.014423919998, "coordinates": {"latitude": 34.0776094459912, "longitude": -118.468632978521}, "is_closed": false, "name": "The Shack In The Back", "price": "$$", "url": "https://www.yelp.com/biz/the-shack-in-the-back-los-angeles?adjust_creative=8_C4NSGbL05eUQksKleGYw&utm_campaign=yelp_api_v3&utm_medium=api_v3_business_search&utm_source=8_C4NSGbL05eUQksKleGYw", "transactions": [], "rating": 4.5, "display_phone": "(310) 440-5546", "categories": [{"alias": "coffee", "title": "Coffee & Tea"}, {"alias": "bagels", "title": "Bagels"}, {"alias": "sandwiches", "title": "Sandwiches"}], "id": "the-shack-in-the-back-los-angeles", "phone": "+13104405546", "image_url": "https://s3-media2.fl.yelpcdn.com/bphoto/gEftdO1ULEFgQGfXVwO9_g/o.jpg", "location": {"state": "CA", "address1": "The Bel Air", "display_address": ["The Bel Air", "662 N Sepulveda Blvd", "Los Angeles, CA 90049"], "city": "Los Angeles", "address2": "662 N Sepulveda Blvd", "address3": "", "country": "US", "zip_code": "90049"}}, {"review_count": 202, "distance": 11789.458835121999, "coordinates": {"latitude": 34.028839096427, "longitude": -118.443034887314}, "is_closed": false, "name": "The Carving Board", "price": "$$", "url": "https://www.yelp.com/biz/the-carving-board-los-angeles-2?adjust_creative=8_C4NSGbL05eUQksKleGYw&utm_campaign=yelp_api_v3&utm_medium=api_v3_business_search&utm_source=8_C4NSGbL05eUQksKleGYw", "transactions": ["delivery"], "rating": 4.5, "display_phone": "(310) 478-7500", "categories": [{"alias": "sandwiches", "title": "Sandwiches"}], "id": "the-carving-board-los-angeles-2", "phone": "+13104787500", "image_url": "https://s3-media1.fl.yelpcdn.com/bphoto/g9axC5tryV2h3LLH8yNn0A/o.jpg", "location": {"state": "CA", "address1": "11676 Gateway Blvd", "display_address": ["11676 Gateway Blvd", "Los Angeles, CA 90064"], "city": "Los Angeles", "address2": "", "address3": "", "country": "US", "zip_code": "90064"}}, {"review_count": 1009, "distance": 8551.22809, "coordinates": {"latitude": 34.039413, "longitude": -118.232504}, "is_closed": false, "name": "Zinc Cafe & Market", "price": "$$", "url": "https://www.yelp.com/biz/zinc-cafe-and-market-los-angeles-5?adjust_creative=8_C4NSGbL05eUQksKleGYw&utm_campaign=yelp_api_v3&utm_medium=api_v3_business_search&utm_source=8_C4NSGbL05eUQksKleGYw", "transactions": ["pickup"], "rating": 4.0, "display_phone": "(323) 825-5381", "categories": [{"alias": "breakfast_brunch", "title": "Breakfast & Brunch"}, {"alias": "vegetarian", "title": "Vegetarian"}], "id": "zinc-cafe-and-market-los-angeles-5", "phone": "+13238255381", "image_url": "https://s3-media4.fl.yelpcdn.com/bphoto/Rnmbi3ztF8Yl2sPPy1leWA/o.jpg", "location": {"state": "CA", "address1": "580 Mateo St", "display_address": ["580 Mateo St", "Los Angeles, CA 90013"], "city": "Los Angeles", "address2": "", "address3": "", "country": "US", "zip_code": "90013"}}, {"review_count": 630, "distance": 7055.37713746, "coordinates": {"latitude": 34.05548, "longitude": -118.39761}, "is_closed": false, "name": "Sotto", "price": "$$$", "url": "https://www.yelp.com/biz/sotto-los-angeles?adjust_creative=8_C4NSGbL05eUQksKleGYw&utm_campaign=yelp_api_v3&utm_medium=api_v3_business_search&utm_source=8_C4NSGbL05eUQksKleGYw", "transactions": [], "rating": 4.0, "display_phone": "(310) 277-0210", "categories": [{"alias": "italian", "title": "Italian"}, {"alias": "pizza", "title": "Pizza"}], "id": "sotto-los-angeles", "phone": "+13102770210", "image_url": "https://s3-media2.fl.yelpcdn.com/bphoto/QAtpapXPjpGJUoRaKHN-iQ/o.jpg", "location": {"state": "CA", "address1": "9575 W Pico Blvd", "display_address": ["9575 W Pico Blvd", "Los Angeles, CA 90035"], "city": "Los Angeles", "address2": "", "address3": "", "country": "US", "zip_code": "90035"}}, {"review_count": 415, "distance": 13517.839622779999, "coordinates": {"latitude": 34.0530451, "longitude": -118.46741}, "is_closed": false, "name": "Pizzicotto", "price": "$$", "url": "https://www.yelp.com/biz/pizzicotto-los-angeles?adjust_creative=8_C4NSGbL05eUQksKleGYw&utm_campaign=yelp_api_v3&utm_medium=api_v3_business_search&utm_source=8_C4NSGbL05eUQksKleGYw", "transactions": ["delivery"], "rating": 4.0, "display_phone": "(310) 442-7188", "categories": [{"alias": "italian", "title": "Italian"}], "id": "pizzicotto-los-angeles", "phone": "+13104427188", "image_url": "https://s3-media3.fl.yelpcdn.com/bphoto/nCmoJW-xvynGP4JM2KMraA/o.jpg", "location": {"state": "CA", "address1": "11758 San Vicente Blvd", "display_address": ["11758 San Vicente Blvd", "Los Angeles, CA 90049"], "city": "Los Angeles", "address2": "", "address3": "", "country": "US", "zip_code": "90049"}}, {"review_count": 73, "distance": 5894.011088652, "coordinates": {"latitude": 34.0773389, "longitude": -118.2606649}, "is_closed": false, "name": "Street Level Cafe", "price": "$$", "url": "https://www.yelp.com/biz/street-level-cafe-los-angeles?adjust_creative=8_C4NSGbL05eUQksKleGYw&utm_campaign=yelp_api_v3&utm_medium=api_v3_business_search&utm_source=8_C4NSGbL05eUQksKleGYw", "transactions": ["pickup"], "rating": 4.5, "display_phone": "(213) 413-2233", "categories": [{"alias": "cafes", "title": "Cafes"}, {"alias": "breakfast_brunch", "title": "Breakfast & Brunch"}, {"alias": "desserts", "title": "Desserts"}], "id": "street-level-cafe-los-angeles", "phone": "+12134132233", "image_url": "https://s3-media3.fl.yelpcdn.com/bphoto/e4S4gqvfzG5wqQ8iuFf-HQ/o.jpg", "location": {"state": "CA", "address1": "1166 Glendale Blvd", "display_address": ["1166 Glendale Blvd", "Los Angeles, CA 90026"], "city": "Los Angeles", "address2": "", "address3": null, "country": "US", "zip_code": "90026"}}, {"review_count": 73, "distance": 15858.81938292, "coordinates": {"latitude": 33.9921777, "longitude": -118.4717115}, "is_closed": false, "name": "Casa Linda", "price": "$$", "url": "https://www.yelp.com/biz/casa-linda-los-angeles-3?adjust_creative=8_C4NSGbL05eUQksKleGYw&utm_campaign=yelp_api_v3&utm_medium=api_v3_business_search&utm_source=8_C4NSGbL05eUQksKleGYw", "transactions": ["delivery", "pickup"], "rating": 4.0, "display_phone": "(310) 664-1177", "categories": [{"alias": "mexican", "title": "Mexican"}], "id": "casa-linda-los-angeles-3", "phone": "+13106641177", "image_url": "https://s3-media3.fl.yelpcdn.com/bphoto/Om7_fgXb9MEA6mL_DAH7vg/o.jpg", "location": {"state": "CA", "address1": "1025 Abbot Kinney Blvd", "display_address": ["1025 Abbot Kinney Blvd", "Los Angeles, CA 90291"], "city": "Los Angeles", "address2": "", "address3": "", "country": "US", "zip_code": "90291"}}, {"review_count": 639, "distance": 5821.570832836, "coordinates": {"latitude": 34.0782765, "longitude": -118.2614713}, "is_closed": false, "name": "Taix French Restaurant", "price": "$$", "url": "https://www.yelp.com/biz/taix-french-country-cuisine-los-angeles?adjust_creative=8_C4NSGbL05eUQksKleGYw&utm_campaign=yelp_api_v3&utm_medium=api_v3_business_search&utm_source=8_C4NSGbL05eUQksKleGYw", "transactions": [], "rating": 4.0, "display_phone": "(213) 484-1265", "categories": [{"alias": "french", "title": "French"}, {"alias": "lounges", "title": "Lounges"}], "id": "taix-french-country-cuisine-los-angeles", "phone": "+12134841265", "image_url": "https://s3-media4.fl.yelpcdn.com/bphoto/RNwP8MTxO9FmU57BOkaD2A/o.jpg", "location": {"state": "CA", "address1": "1911 W Sunset Blvd", "display_address": ["1911 W Sunset Blvd", "Los Angeles, CA 90026"], "city": "Los Angeles", "address2": "", "address3": "", "country": "US", "zip_code": "90026"}}, {"review_count": 10, "distance": 14351.84306296, "coordinates": {"latitude": 34.1271835934512, "longitude": -118.187152817845}, "is_closed": false, "name": "Provecho/Highland Market", "price": "$", "url": "https://www.yelp.com/biz/provecho-highland-market-los-angeles?adjust_creative=8_C4NSGbL05eUQksKleGYw&utm_campaign=yelp_api_v3&utm_medium=api_v3_business_search&utm_source=8_C4NSGbL05eUQksKleGYw", "transactions": [], "rating": 5.0, "display_phone": "(323) 256-7118", "categories": [{"alias": "mexican", "title": "Mexican"}, {"alias": "beer_and_wine", "title": "Beer, Wine & Spirits"}, {"alias": "grocery", "title": "Grocery"}], "id": "provecho-highland-market-los-angeles", "phone": "+13232567118", "image_url": "https://s3-media2.fl.yelpcdn.com/bphoto/RD_xOniCS15XW7yj7Bp8iQ/o.jpg", "location": {"state": "CA", "address1": "6901 N Figueroa St", "display_address": ["6901 N Figueroa St", "Los Angeles, CA 90042"], "city": "Los Angeles", "address2": "", "address3": "", "country": "US", "zip_code": "90042"}}, {"review_count": 474, "distance": 4610.170564362, "coordinates": {"latitude": 34.0861279836519, "longitude": -118.361727050726}, "is_closed": false, "name": "Fat Dog", "price": "$$", "url": "https://www.yelp.com/biz/fat-dog-los-angeles?adjust_creative=8_C4NSGbL05eUQksKleGYw&utm_campaign=yelp_api_v3&utm_medium=api_v3_business_search&utm_source=8_C4NSGbL05eUQksKleGYw", "transactions": ["pickup"], "rating": 4.0, "display_phone": "(323) 951-0030", "categories": [{"alias": "newamerican", "title": "American (New)"}, {"alias": "gastropubs", "title": "Gastropubs"}], "id": "fat-dog-los-angeles", "phone": "+13239510030", "image_url": "https://s3-media4.fl.yelpcdn.com/bphoto/jpH7cURr3tN100kdZf84Tg/o.jpg", "location": {"state": "CA", "address1": "801 N Fairfax Ave", "display_address": ["801 N Fairfax Ave", "Los Angeles, CA 90046"], "city": "Los Angeles", "address2": "", "address3": "", "country": "US", "zip_code": "90046"}}, {"review_count": 2914, "distance": 4115.61668088, "coordinates": {"latitude": 34.098595, "longitude": -118.322208}, "is_closed": false, "name": "Roscoe's House of Chicken & Waffles", "price": "$$", "url": "https://www.yelp.com/biz/roscoes-house-of-chicken-and-waffles-los-angeles-3?adjust_creative=8_C4NSGbL05eUQksKleGYw&utm_campaign=yelp_api_v3&utm_medium=api_v3_business_search&utm_source=8_C4NSGbL05eUQksKleGYw", "transactions": ["delivery", "pickup"], "rating": 4.0, "display_phone": "(323) 466-7453", "categories": [{"alias": "breakfast_brunch", "title": "Breakfast & Brunch"}, {"alias": "soulfood", "title": "Soul Food"}, {"alias": "waffles", "title": "Waffles"}], "id": "roscoes-house-of-chicken-and-waffles-los-angeles-3", "phone": "+13234667453", "image_url": "https://s3-media1.fl.yelpcdn.com/bphoto/WtKcR8b6_6h1bXW_ZqKr_g/o.jpg", "location": {"state": "CA", "address1": "1514 N Gower St", "display_address": ["1514 N Gower St", "Los Angeles, CA 90028"], "city": "Los Angeles", "address2": "", "address3": "", "country": "US", "zip_code": "90028"}}, {"review_count": 134, "distance": 7423.282883104001, "coordinates": {"latitude": 34.0482589, "longitude": -118.2423212}, "is_closed": false, "name": "Baldoria", "price": "$$", "url": "https://www.yelp.com/biz/baldoria-los-angeles?adjust_creative=8_C4NSGbL05eUQksKleGYw&utm_campaign=yelp_api_v3&utm_medium=api_v3_business_search&utm_source=8_C4NSGbL05eUQksKleGYw", "transactions": [], "rating": 4.5, "display_phone": "(213) 947-3329", "categories": [{"alias": "cocktailbars", "title": "Cocktail Bars"}, {"alias": "pizza", "title": "Pizza"}], "id": "baldoria-los-angeles", "phone": "+12139473329", "image_url": "https://s3-media2.fl.yelpcdn.com/bphoto/9xy8UkiWynmsinsQuHRcng/o.jpg", "location": {"state": "CA", "address1": "243 S San Pedro St", "display_address": ["243 S San Pedro St", "Los Angeles, CA 90012"], "city": "Los Angeles", "address2": "", "address3": "", "country": "US", "zip_code": "90012"}}, {"review_count": 10, "distance": 2227.97753803, "coordinates": {"latitude": 34.0631113612969, "longitude": -118.297262431937}, "is_closed": false, "name": "Red Cape", "price": "$", "url": "https://www.yelp.com/biz/red-cape-los-angeles?adjust_creative=8_C4NSGbL05eUQksKleGYw&utm_campaign=yelp_api_v3&utm_medium=api_v3_business_search&utm_source=8_C4NSGbL05eUQksKleGYw", "transactions": [], "rating": 5.0, "display_phone": "(213) 352-1322", "categories": [{"alias": "diyfood", "title": "Do-It-Yourself Food"}, {"alias": "korean", "title": "Korean"}], "id": "red-cape-los-angeles", "phone": "+12133521322", "image_url": "https://s3-media4.fl.yelpcdn.com/bphoto/k3PhQlPsFxFf_xTy_w96Dg/o.jpg", "location": {"state": "CA", "address1": "3450 West 6th St", "display_address": ["3450 West 6th St", "Ste 107", "Los Angeles, CA 90010"], "city": "Los Angeles", "address2": "Ste 107", "address3": null, "country": "US", "zip_code": "90010"}}, {"review_count": 145, "distance": 13614.35335192, "coordinates": {"latitude": 34.0662436840005, "longitude": -118.469063537192}, "is_closed": false, "name": "Il Piccolo Verde", "price": "$$", "url": "https://www.yelp.com/biz/il-piccolo-verde-los-angeles?adjust_creative=8_C4NSGbL05eUQksKleGYw&utm_campaign=yelp_api_v3&utm_medium=api_v3_business_search&utm_source=8_C4NSGbL05eUQksKleGYw", "transactions": ["pickup", "delivery"], "rating": 3.5, "display_phone": "(310) 472-4939", "categories": [{"alias": "italian", "title": "Italian"}], "id": "il-piccolo-verde-los-angeles", "phone": "+13104724939", "image_url": "https://s3-media4.fl.yelpcdn.com/bphoto/24C03Mfnn-un3p6ZVU1Aug/o.jpg", "location": {"state": "CA", "address1": "140 S Barrington Pl", "display_address": ["140 S Barrington Pl", "Los Angeles, CA 90049"], "city": "Los Angeles", "address2": null, "address3": "", "country": "US", "zip_code": "90049"}}, {"review_count": 98, "distance": 2206.3914606099997, "coordinates": {"latitude": 34.0632050066826, "longitude": -118.297504548308}, "is_closed": false, "name": "Choe Gang Jip", "price": "$$", "url": "https://www.yelp.com/biz/choe-gang-jip-los-angeles-3?adjust_creative=8_C4NSGbL05eUQksKleGYw&utm_campaign=yelp_api_v3&utm_medium=api_v3_business_search&utm_source=8_C4NSGbL05eUQksKleGYw", "transactions": [], "rating": 4.5, "display_phone": "(213) 388-0410", "categories": [{"alias": "korean", "title": "Korean"}], "id": "choe-gang-jip-los-angeles-3", "phone": "+12133880410", "image_url": "https://s3-media3.fl.yelpcdn.com/bphoto/6kcZPdl3qO0nx2uDWl1jNw/o.jpg", "location": {"state": "CA", "address1": "3470 W 6th St", "display_address": ["3470 W 6th St", "Ste 3", "Los Angeles, CA 90020"], "city": "Los Angeles", "address2": "Ste 3", "address3": "", "country": "US", "zip_code": "90020"}}, {"review_count": 50, "distance": 11366.0924972, "coordinates": {"latitude": 33.960014966312, "longitude": -118.308071861389}, "is_closed": false, "name": "La Valentina Mexican Grill", "price": "$", "url": "https://www.yelp.com/biz/la-valentina-mexican-grill-los-angeles-3?adjust_creative=8_C4NSGbL05eUQksKleGYw&utm_campaign=yelp_api_v3&utm_medium=api_v3_business_search&utm_source=8_C4NSGbL05eUQksKleGYw", "transactions": [], "rating": 4.5, "display_phone": "(323) 541-9901", "categories": [{"alias": "mexican", "title": "Mexican"}, {"alias": "sportsbars", "title": "Sports Bars"}], "id": "la-valentina-mexican-grill-los-angeles-3", "phone": "+13235419901", "image_url": "https://s3-media4.fl.yelpcdn.com/bphoto/PlPMKCFarAHSauasf59gmw/o.jpg", "location": {"state": "CA", "address1": "1735 West Manchester Ave", "display_address": ["1735 West Manchester Ave", "Los Angeles, CA 90047"], "city": "Los Angeles", "address2": "", "address3": "", "country": "US", "zip_code": "90047"}}, {"review_count": 6, "distance": 6482.191867181999, "coordinates": {"latitude": 34.0418940494564, "longitude": -118.255154863}, "is_closed": false, "name": "Ant", "price": "$$$$", "url": "https://www.yelp.com/biz/ant-los-angeles-2?adjust_creative=8_C4NSGbL05eUQksKleGYw&utm_campaign=yelp_api_v3&utm_medium=api_v3_business_search&utm_source=8_C4NSGbL05eUQksKleGYw", "transactions": [], "rating": 5.0, "display_phone": "(310) 460-8178", "categories": [{"alias": "italian", "title": "Italian"}, {"alias": "modern_european", "title": "Modern European"}], "id": "ant-los-angeles-2", "phone": "+13104608178", "image_url": "https://s3-media1.fl.yelpcdn.com/bphoto/WEcaz3OCiKh6_qaNqjIdhg/o.jpg", "location": {"state": "CA", "address1": "107 W 9th St", "display_address": ["107 W 9th St", "Los Angeles, CA 90015"], "city": "Los Angeles", "address2": "", "address3": "", "country": "US", "zip_code": "90015"}}, {"review_count": 314, "distance": 4547.176812478, "coordinates": {"latitude": 34.0252342224121, "longitude": -118.29857635498}, "is_closed": false, "name": "Revolutionario: North African Tacos", "price": "$", "url": "https://www.yelp.com/biz/revolutionario-north-african-tacos-los-angeles?adjust_creative=8_C4NSGbL05eUQksKleGYw&utm_campaign=yelp_api_v3&utm_medium=api_v3_business_search&utm_source=8_C4NSGbL05eUQksKleGYw", "transactions": [], "rating": 4.5, "display_phone": "(424) 223-3526", "categories": [{"alias": "african", "title": "African"}, {"alias": "mexican", "title": "Mexican"}, {"alias": "halal", "title": "Halal"}], "id": "revolutionario-north-african-tacos-los-angeles", "phone": "+14242233526", "image_url": "https://s3-media3.fl.yelpcdn.com/bphoto/CXGkg5xuTNCBsWSuUPs6dQ/o.jpg", "location": {"state": "CA", "address1": "1436 W Jefferson Blvd", "display_address": ["1436 W Jefferson Blvd", "Ste 70", "Los Angeles, CA 90007"], "city": "Los Angeles", "address2": "Ste 70", "address3": "", "country": "US", "zip_code": "90007"}}, {"review_count": 195, "distance": 5120.103622752, "coordinates": {"latitude": 34.07299, "longitude": -118.37539}, "is_closed": false, "name": "ROC Beverly Grove", "price": "$$", "url": "https://www.yelp.com/biz/roc-beverly-grove-los-angeles-2?adjust_creative=8_C4NSGbL05eUQksKleGYw&utm_campaign=yelp_api_v3&utm_medium=api_v3_business_search&utm_source=8_C4NSGbL05eUQksKleGYw", "transactions": ["pickup"], "rating": 4.0, "display_phone": "(323) 782-8808", "categories": [{"alias": "chinese", "title": "Chinese"}, {"alias": "taiwanese", "title": "Taiwanese"}], "id": "roc-beverly-grove-los-angeles-2", "phone": "+13237828808", "image_url": "https://s3-media2.fl.yelpcdn.com/bphoto/7tVe4u4uB0yCKfcap3WD8Q/o.jpg", "location": {"state": "CA", "address1": "8474 W 3rd St", "display_address": ["8474 W 3rd St", "Ste 108", "Los Angeles, CA 90048"], "city": "Los Angeles", "address2": "Ste 108", "address3": "", "country": "US", "zip_code": "90048"}}, {"review_count": 139, "distance": 3608.808477968, "coordinates": {"latitude": 34.08331, "longitude": -118.35059}, "is_closed": false, "name": "Kawaba Rice Ball", "price": "$", "url": "https://www.yelp.com/biz/kawaba-rice-ball-los-angeles?adjust_creative=8_C4NSGbL05eUQksKleGYw&utm_campaign=yelp_api_v3&utm_medium=api_v3_business_search&utm_source=8_C4NSGbL05eUQksKleGYw", "transactions": ["pickup"], "rating": 4.0, "display_phone": "(323) 272-4510", "categories": [{"alias": "japanese", "title": "Japanese"}, {"alias": "delis", "title": "Delis"}, {"alias": "soup", "title": "Soup"}], "id": "kawaba-rice-ball-los-angeles", "phone": "+13232724510", "image_url": "https://s3-media3.fl.yelpcdn.com/bphoto/2BodJZPN3R1MXjiZmt0Stg/o.jpg", "location": {"state": "CA", "address1": "7368 Melrose Ave", "display_address": ["7368 Melrose Ave", "Los Angeles, CA 90046"], "city": "Los Angeles", "address2": null, "address3": "", "country": "US", "zip_code": "90046"}}, {"review_count": 1333, "distance": 2199.585722684, "coordinates": {"latitude": 34.0640202245113, "longitude": -118.297687050455}, "is_closed": false, "name": "Quarters Korean BBQ", "price": "$$", "url": "https://www.yelp.com/biz/quarters-korean-bbq-los-angeles?adjust_creative=8_C4NSGbL05eUQksKleGYw&utm_campaign=yelp_api_v3&utm_medium=api_v3_business_search&utm_source=8_C4NSGbL05eUQksKleGYw", "transactions": [], "rating": 4.0, "display_phone": "(213) 365-8111", "categories": [{"alias": "korean", "title": "Korean"}, {"alias": "bbq", "title": "Barbeque"}, {"alias": "tapas", "title": "Tapas Bars"}], "id": "quarters-korean-bbq-los-angeles", "phone": "+12133658111", "image_url": "https://s3-media2.fl.yelpcdn.com/bphoto/2EejmTkyisjIt4t7gBKiQw/o.jpg", "location": {"state": "CA", "address1": "3465 W 6th St", "display_address": ["3465 W 6th St", "C-130", "Los Angeles, CA 90020"], "city": "Los Angeles", "address2": "C-130", "address3": "", "country": "US", "zip_code": "90020"}}, {"review_count": 72, "distance": 1341.839206682, "coordinates": {"latitude": 34.06876, "longitude": -118.30948}, "is_closed": false, "name": "Tasty Grill", "price": "$$", "url": "https://www.yelp.com/biz/tasty-grill-los-angeles?adjust_creative=8_C4NSGbL05eUQksKleGYw&utm_campaign=yelp_api_v3&utm_medium=api_v3_business_search&utm_source=8_C4NSGbL05eUQksKleGYw", "transactions": [], "rating": 4.0, "display_phone": "(213) 908-5929", "categories": [{"alias": "korean", "title": "Korean"}, {"alias": "asianfusion", "title": "Asian Fusion"}], "id": "tasty-grill-los-angeles", "phone": "+12139085929", "image_url": "https://s3-media2.fl.yelpcdn.com/bphoto/lszfynTVaurhfbqXgmm_fA/o.jpg", "location": {"state": "CA", "address1": "301 S Western Ave", "display_address": ["301 S Western Ave", "Ste 101-102", "Los Angeles, CA 90020"], "city": "Los Angeles", "address2": "Ste 101-102", "address3": "", "country": "US", "zip_code": "90020"}}, {"review_count": 614, "distance": 2248.906360994, "coordinates": {"latitude": 34.0639524100161, "longitude": -118.29713084418}, "is_closed": false, "name": "Escala", "price": "$$", "url": "https://www.yelp.com/biz/escala-los-angeles-2?adjust_creative=8_C4NSGbL05eUQksKleGYw&utm_campaign=yelp_api_v3&utm_medium=api_v3_business_search&utm_source=8_C4NSGbL05eUQksKleGYw", "transactions": [], "rating": 4.0, "display_phone": "(213) 387-1113", "categories": [{"alias": "colombian", "title": "Colombian"}, {"alias": "gastropubs", "title": "Gastropubs"}, {"alias": "cocktailbars", "title": "Cocktail Bars"}], "id": "escala-los-angeles-2", "phone": "+12133871113", "image_url": "https://s3-media1.fl.yelpcdn.com/bphoto/zwSChH3KFHrJojmMYRd4ww/o.jpg", "location": {"state": "CA", "address1": "3451 W 6th St", "display_address": ["3451 W 6th St", "Los Angeles, CA 90020"], "city": "Los Angeles", "address2": "", "address3": "", "country": "US", "zip_code": "90020"}}, {"review_count": 249, "distance": 11393.197001479999, "coordinates": {"latitude": 34.038391, "longitude": -118.441835}, "is_closed": false, "name": "Morinoya", "price": "$$", "url": "https://www.yelp.com/biz/morinoya-los-angeles?adjust_creative=8_C4NSGbL05eUQksKleGYw&utm_campaign=yelp_api_v3&utm_medium=api_v3_business_search&utm_source=8_C4NSGbL05eUQksKleGYw", "transactions": [], "rating": 4.0, "display_phone": "(310) 473-3960", "categories": [{"alias": "tapasmallplates", "title": "Tapas/Small Plates"}, {"alias": "izakaya", "title": "Izakaya"}], "id": "morinoya-los-angeles", "phone": "+13104733960", "image_url": "https://s3-media3.fl.yelpcdn.com/bphoto/DMu4dY1F98u_Npnnw_a12Q/o.jpg", "location": {"state": "CA", "address1": "11301 W Olympic Blvd", "display_address": ["11301 W Olympic Blvd", "Ste 210", "Los Angeles, CA 90064"], "city": "Los Angeles", "address2": "Ste 210", "address3": "", "country": "US", "zip_code": "90064"}}, {"review_count": 438, "distance": 8666.12852864, "coordinates": {"latitude": 33.9886372, "longitude": -118.354468}, "is_closed": false, "name": "Simply Wholesome", "price": "$$", "url": "https://www.yelp.com/biz/simply-wholesome-los-angeles?adjust_creative=8_C4NSGbL05eUQksKleGYw&utm_campaign=yelp_api_v3&utm_medium=api_v3_business_search&utm_source=8_C4NSGbL05eUQksKleGYw", "transactions": [], "rating": 4.0, "display_phone": "(323) 294-2144", "categories": [{"alias": "soulfood", "title": "Soul Food"}, {"alias": "caribbean", "title": "Caribbean"}, {"alias": "vegetarian", "title": "Vegetarian"}], "id": "simply-wholesome-los-angeles", "phone": "+13232942144", "image_url": "https://s3-media3.fl.yelpcdn.com/bphoto/xrPHstEmsXs87PnohTkXgA/o.jpg", "location": {"state": "CA", "address1": "4508 W Slauson Ave", "display_address": ["4508 W Slauson Ave", "Los Angeles, CA 90043"], "city": "Los Angeles", "address2": "", "address3": "", "country": "US", "zip_code": "90043"}}, {"review_count": 519, "distance": 6213.889783478, "coordinates": {"latitude": 34.0161896, "longitude": -118.2816772}, "is_closed": false, "name": "Lotus", "price": "$$", "url": "https://www.yelp.com/biz/lotus-los-angeles-3?adjust_creative=8_C4NSGbL05eUQksKleGYw&utm_campaign=yelp_api_v3&utm_medium=api_v3_business_search&utm_source=8_C4NSGbL05eUQksKleGYw", "transactions": [], "rating": 4.0, "display_phone": "(213) 478-0090", "categories": [{"alias": "hookah_bars", "title": "Hookah Bars"}, {"alias": "sushi", "title": "Sushi Bars"}, {"alias": "asianfusion", "title": "Asian Fusion"}], "id": "lotus-los-angeles-3", "phone": "+12134780090", "image_url": "https://s3-media3.fl.yelpcdn.com/bphoto/W6DcmBwbCVhU5RK8ibOd5Q/o.jpg", "location": {"state": "CA", "address1": "3742 S Flower St", "display_address": ["3742 S Flower St", "Los Angeles, CA 90007"], "city": "Los Angeles", "address2": "", "address3": "", "country": "US", "zip_code": "90007"}}, {"review_count": 949, "distance": 12397.244110729998, "coordinates": {"latitude": 34.0439999, "longitude": -118.45439}, "is_closed": false, "name": "Nook Bistro", "price": "$$", "url": "https://www.yelp.com/biz/nook-bistro-los-angeles-2?adjust_creative=8_C4NSGbL05eUQksKleGYw&utm_campaign=yelp_api_v3&utm_medium=api_v3_business_search&utm_source=8_C4NSGbL05eUQksKleGYw", "transactions": ["delivery", "pickup"], "rating": 4.0, "display_phone": "(310) 207-5160", "categories": [{"alias": "newamerican", "title": "American (New)"}, {"alias": "beer_and_wine", "title": "Beer, Wine & Spirits"}, {"alias": "cocktailbars", "title": "Cocktail Bars"}], "id": "nook-bistro-los-angeles-2", "phone": "+13102075160", "image_url": "https://s3-media1.fl.yelpcdn.com/bphoto/U5x69RJHSsr4pXicbYZDHg/o.jpg", "location": {"state": "CA", "address1": "11628 Santa Monica Blvd", "display_address": ["11628 Santa Monica Blvd", "Ste 9", "Los Angeles, CA 90025"], "city": "Los Angeles", "address2": "Ste 9", "address3": "", "country": "US", "zip_code": "90025"}}, {"review_count": 912, "distance": 16062.74851036, "coordinates": {"latitude": 34.020057, "longitude": -118.154411}, "is_closed": false, "name": "Tacos Baja Ensenada", "price": "$", "url": "https://www.yelp.com/biz/tacos-baja-ensenada-los-angeles-2?adjust_creative=8_C4NSGbL05eUQksKleGYw&utm_campaign=yelp_api_v3&utm_medium=api_v3_business_search&utm_source=8_C4NSGbL05eUQksKleGYw", "transactions": [], "rating": 4.5, "display_phone": "(323) 887-1980", "categories": [{"alias": "mexican", "title": "Mexican"}], "id": "tacos-baja-ensenada-los-angeles-2", "phone": "+13238871980", "image_url": "https://s3-media1.fl.yelpcdn.com/bphoto/ZxVwtjLW3CAVtl4uWu5xdQ/o.jpg", "location": {"state": "CA", "address1": "5385 Whittier Blvd", "display_address": ["5385 Whittier Blvd", "Los Angeles, CA 90022"], "city": "Los Angeles", "address2": "", "address3": "", "country": "US", "zip_code": "90022"}}, {"review_count": 396, "distance": 11294.052001439999, "coordinates": {"latitude": 34.060031, "longitude": -118.443969}, "is_closed": false, "name": "Skylight Gardens", "price": "$$", "url": "https://www.yelp.com/biz/skylight-gardens-los-angeles?adjust_creative=8_C4NSGbL05eUQksKleGYw&utm_campaign=yelp_api_v3&utm_medium=api_v3_business_search&utm_source=8_C4NSGbL05eUQksKleGYw", "transactions": ["delivery", "pickup"], "rating": 4.0, "display_phone": "(310) 824-1818", "categories": [{"alias": "italian", "title": "Italian"}, {"alias": "cocktailbars", "title": "Cocktail Bars"}, {"alias": "sandwiches", "title": "Sandwiches"}], "id": "skylight-gardens-los-angeles", "phone": "+13108241818", "image_url": "https://s3-media1.fl.yelpcdn.com/bphoto/yH8zV9JmRBx7vPEbEFQRBg/o.jpg", "location": {"state": "CA", "address1": "1139 Glendon Ave", "display_address": ["1139 Glendon Ave", "Los Angeles, CA 90024"], "city": "Los Angeles", "address2": null, "address3": "", "country": "US", "zip_code": "90024"}}]}